[
  {
    "avg_tracks": 20.931034088134766,
    "conflicting_visit_pairs": 5915,
    "conflicts": 33,
    "delay_cost_type": "FiniteSteps123",
    "index": 0,
    "name": "origA1",
    "solves": [
      {
        "algorithm_time": 0.007423338999999999,
        "avg_time_points": 1.5132743362831858,
        "cost": 11,
        "delay_cost_type": "FiniteSteps123",
        "iterations": 127,
        "lb": 11,
        "max_time_points": 7,
        "num_conflicts": 590,
        "num_time_points": 1881,
        "num_traveltime": 590,
        "objective_iters": 11,
        "resource_iters": 1,
        "sol_time": 9.128778,
        "solver_name": "MaxSatDddLadderRC2",
        "solver_time": 0.001037157,
        "status": "ok",
        "total_time": 0.008459674,
        "travel_and_resource_iters": 23,
        "travel_iters": 91,
        "ub": 11
      }
    ],
    "trains": 29
  },
  {
    "avg_tracks": 19.0,
    "conflicting_visit_pairs": 3735,
    "conflicts": 33,
    "delay_cost_type": "FiniteSteps123",
    "index": 1,
    "name": "origA2",
    "solves": [
      {
        "algorithm_time": 0.003879938,
        "avg_time_points": 1.5887179487179488,
        "cost": 25,
        "delay_cost_type": "FiniteSteps123",
        "iterations": 101,
        "lb": 25,
        "max_time_points": 6,
        "num_conflicts": 516,
        "num_time_points": 1549,
        "num_traveltime": 516,
        "objective_iters": 25,
        "resource_iters": 1,
        "sol_time": 4.581361,
        "solver_name": "MaxSatDddLadderRC2",
        "solver_time": 0.000640271,
        "status": "ok",
        "total_time": 0.004519754,
        "travel_and_resource_iters": 20,
        "travel_iters": 54,
        "ub": 25
      }
    ],
    "trains": 25
  },
  {
    "avg_tracks": 22.375,
    "conflicting_visit_pairs": 2061,
    "conflicts": 33,
    "delay_cost_type": "FiniteSteps123",
    "index": 2,
    "name": "origA3",
    "solves": [
      {
        "algorithm_time": 0.003221714,
        "avg_time_points": 1.6980874316939891,
        "cost": 10,
        "delay_cost_type": "FiniteSteps123",
        "iterations": 92,
        "lb": 10,
        "max_time_points": 8,
        "num_conflicts": 471,
        "num_time_points": 1243,
        "num_traveltime": 471,
        "objective_iters": 10,
        "resource_iters": 2,
        "sol_time": 3.841058,
        "solver_name": "MaxSatDddLadderRC2",
        "solver_time": 0.000569414,
        "status": "ok",
        "total_time": 0.003790638,
        "travel_and_resource_iters": 17,
        "travel_iters": 62,
        "ub": 10
      }
    ],
    "trains": 16
  },
  {
    "avg_tracks": 19.214284896850586,
    "conflicting_visit_pairs": 1175,
    "conflicts": 33,
    "delay_cost_type": "FiniteSteps123",
    "index": 3,
    "name": "origA4",
    "solves": [
      {
        "algorithm_time": 0.005821627,
        "avg_time_points": 2.0634057971014492,
        "cost": 17,
        "delay_cost_type": "FiniteSteps123",
        "iterations": 173,
        "lb": 17,
        "max_time_points": 7,
        "num_conflicts": 546,
        "num_time_points": 1139,
        "num_traveltime": 546,
        "objective_iters": 17,
        "resource_iters": 1,
        "sol_time": 7.146974,
        "solver_name": "MaxSatDddLadderRC2",
        "solver_time": 0.001282574,
        "status": "ok",
        "total_time": 0.007103616,
        "travel_and_resource_iters": 18,
        "travel_iters": 136,
        "ub": 17
      }
    ],
    "trains": 14
  },
  {
    "avg_tracks": 19.25,
    "conflicting_visit_pairs": 876,
    "conflicts": 33,
    "delay_cost_type": "FiniteSteps123",
    "index": 4,
    "name": "origA5",
    "solves": [
      {
        "algorithm_time": 0.004812820000000001,
        "avg_time_points": 1.9409282700421941,
        "cost": 15,
        "delay_cost_type": "FiniteSteps123",
        "iterations": 149,
        "lb": 15,
        "max_time_points": 6,
        "num_conflicts": 417,
        "num_time_points": 920,
        "num_traveltime": 417,
        "objective_iters": 15,
        "resource_iters": 1,
        "sol_time": 5.702456,
        "solver_name": "MaxSatDddLadderRC2",
        "solver_time": 0.000851047,
        "status": "ok",
        "total_time": 0.005663421,
        "travel_and_resource_iters": 12,
        "travel_iters": 120,
        "ub": 15
      }
    ],
    "trains": 12
  },
  {
    "avg_tracks": 18.625,
    "conflicting_visit_pairs": 307,
    "conflicts": 33,
    "delay_cost_type": "FiniteSteps123",
    "index": 5,
    "name": "origA6",
    "solves": [
      {
        "algorithm_time": 0.0019584069999999997,
        "avg_time_points": 1.6993464052287581,
        "cost": 10,
        "delay_cost_type": "FiniteSteps123",
        "iterations": 93,
        "lb": 10,
        "max_time_points": 4,
        "num_conflicts": 204,
        "num_time_points": 520,
        "num_traveltime": 204,
        "objective_iters": 10,
        "resource_iters": 1,
        "sol_time": 2.304103,
        "solver_name": "MaxSatDddLadderRC2",
        "solver_time": 0.000315239,
        "status": "ok",
        "total_time": 0.002273237,
        "travel_and_resource_iters": 3,
        "travel_iters": 78,
        "ub": 10
      }
    ],
    "trains": 8
  },
  {
    "avg_tracks": 12.625,
    "conflicting_visit_pairs": 126,
    "conflicts": 33,
    "delay_cost_type": "FiniteSteps123",
    "index": 6,
    "name": "origA7",
    "solves": [
      {
        "algorithm_time": 0.001234579,
        "avg_time_points": 1.8952380952380952,
        "cost": 10,
        "delay_cost_type": "FiniteSteps123",
        "iterations": 55,
        "lb": 10,
        "max_time_points": 6,
        "num_conflicts": 173,
        "num_time_points": 398,
        "num_traveltime": 173,
        "objective_iters": 10,
        "resource_iters": 1,
        "sol_time": 1.394455,
        "solver_name": "MaxSatDddLadderRC2",
        "solver_time": 0.000133539,
        "status": "ok",
        "total_time": 0.001367734,
        "travel_and_resource_iters": 5,
        "travel_iters": 38,
        "ub": 10
      }
    ],
    "trains": 8
  },
  {
    "avg_tracks": 19.214284896850586,
    "conflicting_visit_pairs": 4877,
    "conflicts": 33,
    "delay_cost_type": "FiniteSteps123",
    "index": 7,
    "name": "origA8",
    "solves": [
      {
        "algorithm_time": 0.016866045000000003,
        "avg_time_points": 3.503623188405797,
        "cost": 31,
        "delay_cost_type": "FiniteSteps123",
        "iterations": 193,
        "lb": 31,
        "max_time_points": 18,
        "num_conflicts": 2463,
        "num_time_points": 3868,
        "num_traveltime": 2463,
        "objective_iters": 31,
        "resource_iters": 1,
        "sol_time": 24.312678000000002,
        "solver_name": "MaxSatDddLadderRC2",
        "solver_time": 0.007260437,
        "status": "ok",
        "total_time": 0.024125873,
        "travel_and_resource_iters": 88,
        "travel_iters": 72,
        "ub": 31
      }
    ],
    "trains": 28
  },
  {
    "avg_tracks": 20.049999237060547,
    "conflicting_visit_pairs": 2616,
    "conflicts": 33,
    "delay_cost_type": "FiniteSteps123",
    "index": 8,
    "name": "origA9",
    "solves": [
      {
        "algorithm_time": 0.0052106159999999995,
        "avg_time_points": 2.1557177615571774,
        "cost": 18,
        "delay_cost_type": "FiniteSteps123",
        "iterations": 130,
        "lb": 18,
        "max_time_points": 10,
        "num_conflicts": 842,
        "num_time_points": 1772,
        "num_traveltime": 842,
        "objective_iters": 18,
        "resource_iters": 1,
        "sol_time": 6.584131,
        "solver_name": "MaxSatDddLadderRC2",
        "solver_time": 0.00128609,
        "status": "ok",
        "total_time": 0.006496258,
        "travel_and_resource_iters": 47,
        "travel_iters": 63,
        "ub": 18
      }
    ],
    "trains": 20
  },
  {
    "avg_tracks": 18.176469802856445,
    "conflicting_visit_pairs": 1632,
    "conflicts": 33,
    "delay_cost_type": "FiniteSteps123",
    "index": 9,
    "name": "origA10",
    "solves": [
      {
        "algorithm_time": 0.0029518780000000002,
        "avg_time_points": 1.910236220472441,
        "cost": 17,
        "delay_cost_type": "FiniteSteps123",
        "iterations": 90,
        "lb": 17,
        "max_time_points": 8,
        "num_conflicts": 513,
        "num_time_points": 1213,
        "num_traveltime": 513,
        "objective_iters": 17,
        "resource_iters": 1,
        "sol_time": 3.707864,
        "solver_name": "MaxSatDddLadderRC2",
        "solver_time": 0.000680919,
        "status": "ok",
        "total_time": 0.003632399,
        "travel_and_resource_iters": 22,
        "travel_iters": 49,
        "ub": 17
      }
    ],
    "trains": 17
  },
  {
    "avg_tracks": 19.83333396911621,
    "conflicting_visit_pairs": 6162,
    "conflicts": 33,
    "delay_cost_type": "FiniteSteps123",
    "index": 10,
    "name": "origA11",
    "solves": [
      {
        "algorithm_time": 0.010612482,
        "avg_time_points": 2.392622950819672,
        "cost": 23,
        "delay_cost_type": "FiniteSteps123",
        "iterations": 137,
        "lb": 23,
        "max_time_points": 9,
        "num_conflicts": 1506,
        "num_time_points": 2919,
        "num_traveltime": 1506,
        "objective_iters": 23,
        "resource_iters": 1,
        "sol_time": 16.030933,
        "solver_name": "MaxSatDddLadderRC2",
        "solver_time": 0.005269046,
        "status": "ok",
        "total_time": 0.015881059,
        "travel_and_resource_iters": 60,
        "travel_iters": 52,
        "ub": 23
      }
    ],
    "trains": 30
  },
  {
    "avg_tracks": 21.714284896850586,
    "conflicting_visit_pairs": 6393,
    "conflicts": 33,
    "delay_cost_type": "FiniteSteps123",
    "index": 11,
    "name": "origA12",
    "solves": [
      {
        "algorithm_time": 0.013945179000000002,
        "avg_time_points": 2.442122186495177,
        "cost": 24,
        "delay_cost_type": "FiniteSteps123",
        "iterations": 155,
        "lb": 24,
        "max_time_points": 8,
        "num_conflicts": 1613,
        "num_time_points": 3038,
        "num_traveltime": 1613,
        "objective_iters": 24,
        "resource_iters": 1,
        "sol_time": 19.8558,
        "solver_name": "MaxSatDddLadderRC2",
        "solver_time": 0.005780543,
        "status": "ok",
        "total_time": 0.019725184,
        "travel_and_resource_iters": 60,
        "travel_iters": 69,
        "ub": 24
      }
    ],
    "trains": 28
  },
  {
    "avg_tracks": 17.33333396911621,
    "conflicting_visit_pairs": 2022,
    "conflicts": 25,
    "delay_cost_type": "FiniteSteps123",
    "index": 12,
    "name": "origB1",
    "solves": [
      {
        "algorithm_time": 0.00110593,
        "avg_time_points": 1.1199376947040498,
        "cost": 4,
        "delay_cost_type": "FiniteSteps123",
        "iterations": 39,
        "lb": 4,
        "max_time_points": 4,
        "num_conflicts": 70,
        "num_time_points": 719,
        "num_traveltime": 70,
        "objective_iters": 4,
        "resource_iters": 1,
        "sol_time": 1.198415,
        "solver_name": "MaxSatDddLadderRC2",
        "solver_time": 0.000045743,
        "status": "ok",
        "total_time": 0.001151117,
        "travel_and_resource_iters": 2,
        "travel_iters": 31,
        "ub": 4
      }
    ],
    "trains": 18
  },
  {
    "avg_tracks": 14.800000190734863,
    "conflicting_visit_pairs": 87,
    "conflicts": 25,
    "delay_cost_type": "FiniteSteps123",
    "index": 13,
    "name": "origB2",
    "solves": [
      {
        "algorithm_time": 0.000993062,
        "avg_time_points": 1.5816993464052287,
        "cost": 5,
        "delay_cost_type": "FiniteSteps123",
        "iterations": 61,
        "lb": 5,
        "max_time_points": 4,
        "num_conflicts": 81,
        "num_time_points": 242,
        "num_traveltime": 81,
        "objective_iters": 5,
        "resource_iters": 1,
        "sol_time": 1.091928,
        "solver_name": "MaxSatDddLadderRC2",
        "solver_time": 0.000081531,
        "status": "ok",
        "total_time": 0.001074218,
        "travel_and_resource_iters": 3,
        "travel_iters": 51,
        "ub": 5
      }
    ],
    "trains": 5
  },
  {
    "avg_tracks": 16.799999237060547,
    "conflicting_visit_pairs": 136,
    "conflicts": 20,
    "delay_cost_type": "FiniteSteps123",
    "index": 14,
    "name": "origB3",
    "solves": [
      {
        "algorithm_time": 0.00110756,
        "avg_time_points": 2.0,
        "cost": 5,
        "delay_cost_type": "FiniteSteps123",
        "iterations": 50,
        "lb": 5,
        "max_time_points": 6,
        "num_conflicts": 160,
        "num_time_points": 346,
        "num_traveltime": 160,
        "objective_iters": 5,
        "resource_iters": 1,
        "sol_time": 1.2883149999999999,
        "solver_name": "MaxSatDddLadderRC2",
        "solver_time": 0.000128299,
        "status": "ok",
        "total_time": 0.00123545,
        "travel_and_resource_iters": 5,
        "travel_iters": 38,
        "ub": 5
      }
    ],
    "trains": 5
  },
  {
    "avg_tracks": 15.949999809265137,
    "conflicting_visit_pairs": 2246,
    "conflicts": 25,
    "delay_cost_type": "FiniteSteps123",
    "index": 15,
    "name": "origB4",
    "solves": [
      {
        "algorithm_time": 0.0037282360000000002,
        "avg_time_points": 2.095744680851064,
        "cost": 16,
        "delay_cost_type": "FiniteSteps123",
        "iterations": 114,
        "lb": 16,
        "max_time_points": 13,
        "num_conflicts": 624,
        "num_time_points": 1379,
        "num_traveltime": 624,
        "objective_iters": 16,
        "resource_iters": 1,
        "sol_time": 4.954518,
        "solver_name": "MaxSatDddLadderRC2",
        "solver_time": 0.001164643,
        "status": "ok",
        "total_time": 0.004892277,
        "travel_and_resource_iters": 46,
        "travel_iters": 50,
        "ub": 16
      }
    ],
    "trains": 20
  },
  {
    "avg_tracks": 17.799999237060547,
    "conflicting_visit_pairs": 136,
    "conflicts": 25,
    "delay_cost_type": "FiniteSteps123",
    "index": 16,
    "name": "origB5",
    "solves": [
      {
        "algorithm_time": 0.001139979,
        "avg_time_points": 1.6010928961748634,
        "cost": 2,
        "delay_cost_type": "FiniteSteps123",
        "iterations": 73,
        "lb": 2,
        "max_time_points": 4,
        "num_conflicts": 102,
        "num_time_points": 293,
        "num_traveltime": 102,
        "objective_iters": 2,
        "resource_iters": 1,
        "sol_time": 1.288778,
        "solver_name": "MaxSatDddLadderRC2",
        "solver_time": 0.000123227,
        "status": "ok",
        "total_time": 0.001262743,
        "travel_and_resource_iters": 3,
        "travel_iters": 66,
        "ub": 2
      }
    ],
    "trains": 5
  },
  {
    "avg_tracks": 15.199999809265137,
    "conflicting_visit_pairs": 93,
    "conflicts": 25,
    "delay_cost_type": "FiniteSteps123",
    "index": 17,
    "name": "origB6",
    "solves": [
      {
        "algorithm_time": 0.000302237,
        "avg_time_points": 1.0955414012738853,
        "cost": 2,
        "delay_cost_type": "FiniteSteps123",
        "iterations": 17,
        "lb": 2,
        "max_time_points": 2,
        "num_conflicts": 13,
        "num_time_points": 172,
        "num_traveltime": 13,
        "objective_iters": 2,
        "resource_iters": 1,
        "sol_time": 0.333699,
        "solver_name": "MaxSatDddLadderRC2",
        "solver_time": 0.000011218,
        "status": "ok",
        "total_time": 0.000312993,
        "travel_and_resource_iters": 0,
        "travel_iters": 13,
        "ub": 2
      }
    ],
    "trains": 5
  },
  {
    "avg_tracks": 15.25,
    "conflicting_visit_pairs": 2865,
    "conflicts": 25,
    "delay_cost_type": "FiniteSteps123",
    "index": 18,
    "name": "origB7",
    "solves": [
      {
        "algorithm_time": 0.0041397249999999995,
        "avg_time_points": 2.8544973544973544,
        "cost": 25,
        "delay_cost_type": "FiniteSteps123",
        "iterations": 86,
        "lb": 25,
        "max_time_points": 18,
        "num_conflicts": 1319,
        "num_time_points": 2158,
        "num_traveltime": 1319,
        "objective_iters": 25,
        "resource_iters": 1,
        "sol_time": 5.8708279999999995,
        "solver_name": "MaxSatDddLadderRC2",
        "solver_time": 0.001668254,
        "status": "ok",
        "total_time": 0.005807472,
        "travel_and_resource_iters": 42,
        "travel_iters": 17,
        "ub": 25
      }
    ],
    "trains": 24
  },
  {
    "avg_tracks": 13.399999618530273,
    "conflicting_visit_pairs": 72,
    "conflicts": 25,
    "delay_cost_type": "FiniteSteps123",
    "index": 19,
    "name": "origB8",
    "solves": [
      {
        "algorithm_time": 0.0007795009999999999,
        "avg_time_points": 1.2949640287769784,
        "cost": 6,
        "delay_cost_type": "FiniteSteps123",
        "iterations": 47,
        "lb": 6,
        "max_time_points": 2,
        "num_conflicts": 39,
        "num_time_points": 180,
        "num_traveltime": 39,
        "objective_iters": 6,
        "resource_iters": 1,
        "sol_time": 0.8630629999999999,
        "solver_name": "MaxSatDddLadderRC2",
        "solver_time": 0.00005226,
        "status": "ok",
        "total_time": 0.000831246,
        "travel_and_resource_iters": 0,
        "travel_iters": 39,
        "ub": 6
      }
    ],
    "trains": 5
  },
  {
    "avg_tracks": 13.571428298950195,
    "conflicting_visit_pairs": 150,
    "conflicts": 25,
    "delay_cost_type": "FiniteSteps123",
    "index": 20,
    "name": "origB9",
    "solves": [
      {
        "algorithm_time": 0.0022856400000000002,
        "avg_time_points": 2.781725888324873,
        "cost": 7,
        "delay_cost_type": "FiniteSteps123",
        "iterations": 96,
        "lb": 7,
        "max_time_points": 8,
        "num_conflicts": 326,
        "num_time_points": 548,
        "num_traveltime": 326,
        "objective_iters": 7,
        "resource_iters": 1,
        "sol_time": 2.776103,
        "solver_name": "MaxSatDddLadderRC2",
        "solver_time": 0.00046674,
        "status": "ok",
        "total_time": 0.002751852,
        "travel_and_resource_iters": 9,
        "travel_iters": 78,
        "ub": 7
      }
    ],
    "trains": 7
  },
  {
    "avg_tracks": 11.375,
    "conflicting_visit_pairs": 130,
    "conflicts": 25,
    "delay_cost_type": "FiniteSteps123",
    "index": 21,
    "name": "origB10",
    "solves": [
      {
        "algorithm_time": 0.002235381,
        "avg_time_points": 2.663157894736842,
        "cost": 10,
        "delay_cost_type": "FiniteSteps123",
        "iterations": 64,
        "lb": 10,
        "max_time_points": 8,
        "num_conflicts": 285,
        "num_time_points": 506,
        "num_traveltime": 285,
        "objective_iters": 10,
        "resource_iters": 1,
        "sol_time": 2.688378,
        "solver_name": "MaxSatDddLadderRC2",
        "solver_time": 0.000428288,
        "status": "ok",
        "total_time": 0.002663177,
        "travel_and_resource_iters": 12,
        "travel_iters": 40,
        "ub": 10
      }
    ],
    "trains": 8
  },
  {
    "avg_tracks": 15.399999618530273,
    "conflicting_visit_pairs": 3202,
    "conflicts": 25,
    "delay_cost_type": "FiniteSteps123",
    "index": 22,
    "name": "origB11",
    "solves": [
      {
        "algorithm_time": 0.005253656,
        "avg_time_points": 2.722012578616352,
        "cost": 23,
        "delay_cost_type": "FiniteSteps123",
        "iterations": 112,
        "lb": 23,
        "max_time_points": 28,
        "num_conflicts": 1270,
        "num_time_points": 2164,
        "num_traveltime": 1270,
        "objective_iters": 23,
        "resource_iters": 1,
        "sol_time": 7.726214000000001,
        "solver_name": "MaxSatDddLadderRC2",
        "solver_time": 0.002417771,
        "status": "ok",
        "total_time": 0.007670958,
        "travel_and_resource_iters": 75,
        "travel_iters": 12,
        "ub": 23
      }
    ],
    "trains": 25
  },
  {
    "avg_tracks": 16.214284896850586,
    "conflicting_visit_pairs": 970,
    "conflicts": 25,
    "delay_cost_type": "FiniteSteps123",
    "index": 23,
    "name": "origB12",
    "solves": [
      {
        "algorithm_time": 0.001555073,
        "avg_time_points": 1.5598290598290598,
        "cost": 6,
        "delay_cost_type": "FiniteSteps123",
        "iterations": 57,
        "lb": 6,
        "max_time_points": 7,
        "num_conflicts": 224,
        "num_time_points": 730,
        "num_traveltime": 224,
        "objective_iters": 6,
        "resource_iters": 1,
        "sol_time": 1.7488359999999998,
        "solver_name": "MaxSatDddLadderRC2",
        "solver_time": 0.00016328,
        "status": "ok",
        "total_time": 0.001717916,
        "travel_and_resource_iters": 16,
        "travel_iters": 33,
        "ub": 6
      }
    ],
    "trains": 14
  },
  {
    "avg_tracks": 20.931034088134766,
    "conflicting_visit_pairs": 5915,
    "conflicts": 33,
    "delay_cost_type": "FiniteSteps123",
    "index": 24,
    "name": "trackA1",
    "solves": [
      {
        "algorithm_time": 0.023879424000000003,
        "avg_time_points": 4.053901850362028,
        "cost": 23,
        "delay_cost_type": "FiniteSteps123",
        "iterations": 199,
        "lb": 23,
        "max_time_points": 27,
        "num_conflicts": 3367,
        "num_time_points": 5039,
        "num_traveltime": 3367,
        "objective_iters": 23,
        "resource_iters": 1,
        "sol_time": 47.793103,
        "solver_name": "MaxSatDddLadderRC2",
        "solver_time": 0.023702463,
        "status": "ok",
        "total_time": 0.04758124,
        "travel_and_resource_iters": 99,
        "travel_iters": 75,
        "ub": 23
      }
    ],
    "trains": 29
  },
  {
    "avg_tracks": 19.0,
    "conflicting_visit_pairs": 3735,
    "conflicts": 33,
    "delay_cost_type": "FiniteSteps123",
    "index": 25,
    "name": "trackA2",
    "solves": [
      {
        "algorithm_time": 0.017854708000000004,
        "avg_time_points": 3.878974358974359,
        "cost": 33,
        "delay_cost_type": "FiniteSteps123",
        "iterations": 161,
        "lb": 33,
        "max_time_points": 16,
        "num_conflicts": 2491,
        "num_time_points": 3782,
        "num_traveltime": 2491,
        "objective_iters": 33,
        "resource_iters": 1,
        "sol_time": 29.386365,
        "solver_name": "MaxSatDddLadderRC2",
        "solver_time": 0.011356462,
        "status": "ok",
        "total_time": 0.029210688,
        "travel_and_resource_iters": 72,
        "travel_iters": 54,
        "ub": 33
      }
    ],
    "trains": 25
  },
  {
    "avg_tracks": 22.375,
    "conflicting_visit_pairs": 2061,
    "conflicts": 33,
    "delay_cost_type": "FiniteSteps123",
    "index": 26,
    "name": "trackA3",
    "solves": [
      {
        "algorithm_time": 0.012180989,
        "avg_time_points": 3.8456284153005464,
        "cost": 15,
        "delay_cost_type": "FiniteSteps123",
        "iterations": 178,
        "lb": 15,
        "max_time_points": 18,
        "num_conflicts": 1906,
        "num_time_points": 2815,
        "num_traveltime": 1906,
        "objective_iters": 15,
        "resource_iters": 1,
        "sol_time": 19.033443000000002,
        "solver_name": "MaxSatDddLadderRC2",
        "solver_time": 0.006725759,
        "status": "ok",
        "total_time": 0.018906228,
        "travel_and_resource_iters": 58,
        "travel_iters": 103,
        "ub": 15
      }
    ],
    "trains": 16
  },
  {
    "avg_tracks": 19.214284896850586,
    "conflicting_visit_pairs": 1175,
    "conflicts": 33,
    "delay_cost_type": "FiniteSteps123",
    "index": 27,
    "name": "trackA4",
    "solves": [
      {
        "algorithm_time": 0.004840972,
        "avg_time_points": 2.8532608695652173,
        "cost": 15,
        "delay_cost_type": "FiniteSteps123",
        "iterations": 108,
        "lb": 15,
        "max_time_points": 15,
        "num_conflicts": 938,
        "num_time_points": 1575,
        "num_traveltime": 938,
        "objective_iters": 15,
        "resource_iters": 2,
        "sol_time": 6.45761,
        "solver_name": "MaxSatDddLadderRC2",
        "solver_time": 0.001548637,
        "status": "ok",
        "total_time": 0.00638912,
        "travel_and_resource_iters": 26,
        "travel_iters": 64,
        "ub": 15
      }
    ],
    "trains": 14
  },
  {
    "avg_tracks": 19.25,
    "conflicting_visit_pairs": 876,
    "conflicts": 33,
    "delay_cost_type": "FiniteSteps123",
    "index": 28,
    "name": "trackA5",
    "solves": [
      {
        "algorithm_time": 0.004452209,
        "avg_time_points": 2.2953586497890295,
        "cost": 12,
        "delay_cost_type": "FiniteSteps123",
        "iterations": 125,
        "lb": 12,
        "max_time_points": 11,
        "num_conflicts": 563,
        "num_time_points": 1088,
        "num_traveltime": 563,
        "objective_iters": 12,
        "resource_iters": 1,
        "sol_time": 5.6755889999999996,
        "solver_name": "MaxSatDddLadderRC2",
        "solver_time": 0.001164726,
        "status": "ok",
        "total_time": 0.005616394,
        "travel_and_resource_iters": 24,
        "travel_iters": 87,
        "ub": 12
      }
    ],
    "trains": 12
  },
  {
    "avg_tracks": 18.625,
    "conflicting_visit_pairs": 307,
    "conflicts": 33,
    "delay_cost_type": "FiniteSteps123",
    "index": 29,
    "name": "trackA6",
    "solves": [
      {
        "algorithm_time": 0.001988101,
        "avg_time_points": 1.869281045751634,
        "cost": 8,
        "delay_cost_type": "FiniteSteps123",
        "iterations": 78,
        "lb": 8,
        "max_time_points": 7,
        "num_conflicts": 246,
        "num_time_points": 572,
        "num_traveltime": 246,
        "objective_iters": 8,
        "resource_iters": 1,
        "sol_time": 2.377076,
        "solver_name": "MaxSatDddLadderRC2",
        "solver_time": 0.00036308,
        "status": "ok",
        "total_time": 0.002350649,
        "travel_and_resource_iters": 7,
        "travel_iters": 61,
        "ub": 8
      }
    ],
    "trains": 8
  },
  {
    "avg_tracks": 12.625,
    "conflicting_visit_pairs": 126,
    "conflicts": 33,
    "delay_cost_type": "FiniteSteps123",
    "index": 30,
    "name": "trackA7",
    "solves": [
      {
        "algorithm_time": 0.0014943180000000001,
        "avg_time_points": 2.080952380952381,
        "cost": 8,
        "delay_cost_type": "FiniteSteps123",
        "iterations": 63,
        "lb": 8,
        "max_time_points": 5,
        "num_conflicts": 211,
        "num_time_points": 437,
        "num_traveltime": 211,
        "objective_iters": 8,
        "resource_iters": 1,
        "sol_time": 1.775601,
        "solver_name": "MaxSatDddLadderRC2",
        "solver_time": 0.000249311,
        "status": "ok",
        "total_time": 0.001743165,
        "travel_and_resource_iters": 5,
        "travel_iters": 48,
        "ub": 8
      }
    ],
    "trains": 8
  },
  {
    "avg_tracks": 19.88888931274414,
    "conflicting_visit_pairs": 4862,
    "conflicts": 33,
    "delay_cost_type": "FiniteSteps123",
    "index": 31,
    "name": "trackA8",
    "solves": [
      {
        "algorithm_time": 0.024171697000000002,
        "avg_time_points": 7.317892824704813,
        "cost": 34,
        "delay_cost_type": "FiniteSteps123",
        "iterations": 159,
        "lb": 34,
        "max_time_points": 38,
        "num_conflicts": 5994,
        "num_time_points": 8057,
        "num_traveltime": 5994,
        "objective_iters": 34,
        "resource_iters": 2,
        "sol_time": 54.367897,
        "solver_name": "MaxSatDddLadderRC2",
        "solver_time": 0.029876637,
        "status": "ok",
        "total_time": 0.054047782,
        "travel_and_resource_iters": 114,
        "travel_iters": 8,
        "ub": 34
      }
    ],
    "trains": 27
  },
  {
    "avg_tracks": 20.049999237060547,
    "conflicting_visit_pairs": 2616,
    "conflicts": 33,
    "delay_cost_type": "FiniteSteps123",
    "index": 32,
    "name": "trackA9",
    "solves": [
      {
        "algorithm_time": 0.011489829,
        "avg_time_points": 3.295620437956204,
        "cost": 25,
        "delay_cost_type": "FiniteSteps123",
        "iterations": 154,
        "lb": 25,
        "max_time_points": 15,
        "num_conflicts": 1670,
        "num_time_points": 2709,
        "num_traveltime": 1670,
        "objective_iters": 25,
        "resource_iters": 1,
        "sol_time": 16.520355000000002,
        "solver_name": "MaxSatDddLadderRC2",
        "solver_time": 0.004909183,
        "status": "ok",
        "total_time": 0.016398473,
        "travel_and_resource_iters": 67,
        "travel_iters": 60,
        "ub": 25
      }
    ],
    "trains": 20
  },
  {
    "avg_tracks": 18.176469802856445,
    "conflicting_visit_pairs": 1632,
    "conflicts": 33,
    "delay_cost_type": "FiniteSteps123",
    "index": 33,
    "name": "trackA10",
    "solves": [
      {
        "algorithm_time": 0.003194059,
        "avg_time_points": 2.3133858267716536,
        "cost": 17,
        "delay_cost_type": "FiniteSteps123",
        "iterations": 76,
        "lb": 17,
        "max_time_points": 12,
        "num_conflicts": 738,
        "num_time_points": 1469,
        "num_traveltime": 738,
        "objective_iters": 17,
        "resource_iters": 1,
        "sol_time": 3.977082,
        "solver_name": "MaxSatDddLadderRC2",
        "solver_time": 0.000740399,
        "status": "ok",
        "total_time": 0.003934038,
        "travel_and_resource_iters": 31,
        "travel_iters": 26,
        "ub": 17
      }
    ],
    "trains": 17
  },
  {
    "avg_tracks": 20.482759475708008,
    "conflicting_visit_pairs": 6144,
    "conflicts": 33,
    "delay_cost_type": "FiniteSteps123",
    "index": 34,
    "name": "trackA11",
    "solves": [
      {
        "algorithm_time": 0.04695346900000001,
        "avg_time_points": 9.341002465078061,
        "cost": 33,
        "delay_cost_type": "FiniteSteps123",
        "iterations": 252,
        "lb": 33,
        "max_time_points": 75,
        "num_conflicts": 8652,
        "num_time_points": 11368,
        "num_traveltime": 8652,
        "objective_iters": 33,
        "resource_iters": 1,
        "sol_time": 140.063007,
        "solver_name": "MaxSatDddLadderRC2",
        "solver_time": 0.092675679,
        "status": "ok",
        "total_time": 0.139628579,
        "travel_and_resource_iters": 188,
        "travel_iters": 29,
        "ub": 33
      }
    ],
    "trains": 29
  },
  {
    "avg_tracks": 21.714284896850586,
    "conflicting_visit_pairs": 6393,
    "conflicts": 33,
    "delay_cost_type": "FiniteSteps123",
    "index": 35,
    "name": "trackA12",
    "solves": [
      {
        "algorithm_time": 0.03436552799999999,
        "avg_time_points": 8.936495176848874,
        "cost": 36,
        "delay_cost_type": "FiniteSteps123",
        "iterations": 184,
        "lb": 36,
        "max_time_points": 74,
        "num_conflicts": 8293,
        "num_time_points": 11117,
        "num_traveltime": 8293,
        "objective_iters": 36,
        "resource_iters": 1,
        "sol_time": 122.405499,
        "solver_name": "MaxSatDddLadderRC2",
        "solver_time": 0.087596506,
        "status": "ok",
        "total_time": 0.12196135,
        "travel_and_resource_iters": 123,
        "travel_iters": 23,
        "ub": 36
      }
    ],
    "trains": 28
  },
  {
    "avg_tracks": 17.33333396911621,
    "conflicting_visit_pairs": 2022,
    "conflicts": 25,
    "delay_cost_type": "FiniteSteps123",
    "index": 36,
    "name": "trackB1",
    "solves": [
      {
        "algorithm_time": 0.0065393510000000005,
        "avg_time_points": 2.641744548286604,
        "cost": 13,
        "delay_cost_type": "FiniteSteps123",
        "iterations": 141,
        "lb": 13,
        "max_time_points": 9,
        "num_conflicts": 981,
        "num_time_points": 1696,
        "num_traveltime": 981,
        "objective_iters": 13,
        "resource_iters": 1,
        "sol_time": 9.171085000000001,
        "solver_name": "MaxSatDddLadderRC2",
        "solver_time": 0.002559541,
        "status": "ok",
        "total_time": 0.009098345,
        "travel_and_resource_iters": 25,
        "travel_iters": 101,
        "ub": 13
      }
    ],
    "trains": 18
  },
  {
    "avg_tracks": 14.800000190734863,
    "conflicting_visit_pairs": 87,
    "conflicts": 25,
    "delay_cost_type": "FiniteSteps123",
    "index": 37,
    "name": "trackB2",
    "solves": [
      {
        "algorithm_time": 0.001319476,
        "avg_time_points": 1.8104575163398693,
        "cost": 5,
        "delay_cost_type": "FiniteSteps123",
        "iterations": 58,
        "lb": 5,
        "max_time_points": 4,
        "num_conflicts": 109,
        "num_time_points": 277,
        "num_traveltime": 109,
        "objective_iters": 5,
        "resource_iters": 2,
        "sol_time": 1.5946790000000002,
        "solver_name": "MaxSatDddLadderRC2",
        "solver_time": 0.000226194,
        "status": "ok",
        "total_time": 0.001545153,
        "travel_and_resource_iters": 3,
        "travel_iters": 47,
        "ub": 5
      }
    ],
    "trains": 5
  },
  {
    "avg_tracks": 16.799999237060547,
    "conflicting_visit_pairs": 136,
    "conflicts": 20,
    "delay_cost_type": "FiniteSteps123",
    "index": 38,
    "name": "trackB3",
    "solves": [
      {
        "algorithm_time": 0.0017869399999999999,
        "avg_time_points": 2.8728323699421967,
        "cost": 4,
        "delay_cost_type": "FiniteSteps123",
        "iterations": 75,
        "lb": 4,
        "max_time_points": 10,
        "num_conflicts": 286,
        "num_time_points": 497,
        "num_traveltime": 286,
        "objective_iters": 4,
        "resource_iters": 1,
        "sol_time": 2.1551489999999998,
        "solver_name": "MaxSatDddLadderRC2",
        "solver_time": 0.00034242,
        "status": "ok",
        "total_time": 0.002128957,
        "travel_and_resource_iters": 18,
        "travel_iters": 51,
        "ub": 4
      }
    ],
    "trains": 5
  },
  {
    "avg_tracks": 15.949999809265137,
    "conflicting_visit_pairs": 2246,
    "conflicts": 25,
    "delay_cost_type": "FiniteSteps123",
    "index": 39,
    "name": "trackB4",
    "solves": [
      {
        "algorithm_time": 0.00568047,
        "avg_time_points": 3.3069908814589666,
        "cost": 19,
        "delay_cost_type": "FiniteSteps123",
        "iterations": 104,
        "lb": 19,
        "max_time_points": 14,
        "num_conflicts": 1320,
        "num_time_points": 2176,
        "num_traveltime": 1320,
        "objective_iters": 19,
        "resource_iters": 1,
        "sol_time": 7.8379650000000005,
        "solver_name": "MaxSatDddLadderRC2",
        "solver_time": 0.002094147,
        "status": "ok",
        "total_time": 0.007774062,
        "travel_and_resource_iters": 56,
        "travel_iters": 27,
        "ub": 19
      }
    ],
    "trains": 20
  },
  {
    "avg_tracks": 17.799999237060547,
    "conflicting_visit_pairs": 136,
    "conflicts": 25,
    "delay_cost_type": "FiniteSteps123",
    "index": 40,
    "name": "trackB5",
    "solves": [
      {
        "algorithm_time": 0.001558047,
        "avg_time_points": 3.3333333333333335,
        "cost": 7,
        "delay_cost_type": "FiniteSteps123",
        "iterations": 65,
        "lb": 7,
        "max_time_points": 9,
        "num_conflicts": 386,
        "num_time_points": 610,
        "num_traveltime": 386,
        "objective_iters": 7,
        "resource_iters": 1,
        "sol_time": 2.070414,
        "solver_name": "MaxSatDddLadderRC2",
        "solver_time": 0.000489818,
        "status": "ok",
        "total_time": 0.002047375,
        "travel_and_resource_iters": 22,
        "travel_iters": 34,
        "ub": 7
      }
    ],
    "trains": 5
  },
  {
    "avg_tracks": 15.199999809265137,
    "conflicting_visit_pairs": 93,
    "conflicts": 25,
    "delay_cost_type": "FiniteSteps123",
    "index": 41,
    "name": "trackB6",
    "solves": [
      {
        "algorithm_time": 0.001150237,
        "avg_time_points": 1.7070063694267517,
        "cost": 2,
        "delay_cost_type": "FiniteSteps123",
        "iterations": 51,
        "lb": 2,
        "max_time_points": 4,
        "num_conflicts": 105,
        "num_time_points": 268,
        "num_traveltime": 105,
        "objective_iters": 2,
        "resource_iters": 1,
        "sol_time": 1.4757850000000001,
        "solver_name": "MaxSatDddLadderRC2",
        "solver_time": 0.000275627,
        "status": "ok",
        "total_time": 0.001425229,
        "travel_and_resource_iters": 1,
        "travel_iters": 46,
        "ub": 2
      }
    ],
    "trains": 5
  },
  {
    "avg_tracks": 15.25,
    "conflicting_visit_pairs": 2865,
    "conflicts": 25,
    "delay_cost_type": "FiniteSteps123",
    "index": 42,
    "name": "trackB7",
    "solves": [
      {
        "algorithm_time": 0.008845863,
        "avg_time_points": 3.0251322751322753,
        "cost": 27,
        "delay_cost_type": "FiniteSteps123",
        "iterations": 126,
        "lb": 27,
        "max_time_points": 13,
        "num_conflicts": 1338,
        "num_time_points": 2287,
        "num_traveltime": 1338,
        "objective_iters": 27,
        "resource_iters": 3,
        "sol_time": 14.705067,
        "solver_name": "MaxSatDddLadderRC2",
        "solver_time": 0.005728604,
        "status": "ok",
        "total_time": 0.014573948,
        "travel_and_resource_iters": 56,
        "travel_iters": 39,
        "ub": 27
      }
    ],
    "trains": 24
  },
  {
    "avg_tracks": 13.399999618530273,
    "conflicting_visit_pairs": 72,
    "conflicts": 25,
    "delay_cost_type": "FiniteSteps123",
    "index": 43,
    "name": "trackB8",
    "solves": [
      {
        "algorithm_time": 0.0017290130000000002,
        "avg_time_points": 2.884892086330935,
        "cost": 8,
        "delay_cost_type": "FiniteSteps123",
        "iterations": 99,
        "lb": 8,
        "max_time_points": 7,
        "num_conflicts": 240,
        "num_time_points": 401,
        "num_traveltime": 240,
        "objective_iters": 8,
        "resource_iters": 1,
        "sol_time": 2.099803,
        "solver_name": "MaxSatDddLadderRC2",
        "solver_time": 0.000333706,
        "status": "ok",
        "total_time": 0.002062261,
        "travel_and_resource_iters": 9,
        "travel_iters": 80,
        "ub": 8
      }
    ],
    "trains": 5
  },
  {
    "avg_tracks": 13.571428298950195,
    "conflicting_visit_pairs": 150,
    "conflicts": 25,
    "delay_cost_type": "FiniteSteps123",
    "index": 44,
    "name": "trackB9",
    "solves": [
      {
        "algorithm_time": 0.0015889009999999998,
        "avg_time_points": 3.248730964467005,
        "cost": 9,
        "delay_cost_type": "FiniteSteps123",
        "iterations": 59,
        "lb": 9,
        "max_time_points": 9,
        "num_conflicts": 376,
        "num_time_points": 640,
        "num_traveltime": 376,
        "objective_iters": 9,
        "resource_iters": 1,
        "sol_time": 2.097623,
        "solver_name": "MaxSatDddLadderRC2",
        "solver_time": 0.000471164,
        "status": "ok",
        "total_time": 0.002059373,
        "travel_and_resource_iters": 27,
        "travel_iters": 21,
        "ub": 9
      }
    ],
    "trains": 7
  },
  {
    "avg_tracks": 12.857142448425293,
    "conflicting_visit_pairs": 126,
    "conflicts": 25,
    "delay_cost_type": "FiniteSteps123",
    "index": 45,
    "name": "trackB10",
    "solves": [
      {
        "algorithm_time": 0.0009466310000000001,
        "avg_time_points": 1.572192513368984,
        "cost": 8,
        "delay_cost_type": "FiniteSteps123",
        "iterations": 49,
        "lb": 8,
        "max_time_points": 4,
        "num_conflicts": 99,
        "num_time_points": 294,
        "num_traveltime": 99,
        "objective_iters": 8,
        "resource_iters": 1,
        "sol_time": 1.0549979999999999,
        "solver_name": "MaxSatDddLadderRC2",
        "solver_time": 0.000076235,
        "status": "ok",
        "total_time": 0.00102244,
        "travel_and_resource_iters": 2,
        "travel_iters": 37,
        "ub": 8
      }
    ],
    "trains": 7
  },
  {
    "avg_tracks": 15.399999618530273,
    "conflicting_visit_pairs": 3202,
    "conflicts": 25,
    "delay_cost_type": "FiniteSteps123",
    "index": 46,
    "name": "trackB11",
    "solves": [
      {
        "algorithm_time": 0.013070935,
        "avg_time_points": 3.7647798742138363,
        "cost": 31,
        "delay_cost_type": "FiniteSteps123",
        "iterations": 173,
        "lb": 31,
        "max_time_points": 15,
        "num_conflicts": 1948,
        "num_time_points": 2993,
        "num_traveltime": 1948,
        "objective_iters": 31,
        "resource_iters": 1,
        "sol_time": 25.006738000000002,
        "solver_name": "MaxSatDddLadderRC2",
        "solver_time": 0.011782744,
        "status": "ok",
        "total_time": 0.024853072,
        "travel_and_resource_iters": 74,
        "travel_iters": 66,
        "ub": 31
      }
    ],
    "trains": 25
  },
  {
    "avg_tracks": 16.214284896850586,
    "conflicting_visit_pairs": 970,
    "conflicts": 25,
    "delay_cost_type": "FiniteSteps123",
    "index": 47,
    "name": "trackB12",
    "solves": [
      {
        "algorithm_time": 0.004151336,
        "avg_time_points": 3.0277777777777777,
        "cost": 16,
        "delay_cost_type": "FiniteSteps123",
        "iterations": 116,
        "lb": 16,
        "max_time_points": 16,
        "num_conflicts": 823,
        "num_time_points": 1417,
        "num_traveltime": 823,
        "objective_iters": 16,
        "resource_iters": 1,
        "sol_time": 6.055249000000001,
        "solver_name": "MaxSatDddLadderRC2",
        "solver_time": 0.001847791,
        "status": "ok",
        "total_time": 0.00599863,
        "travel_and_resource_iters": 45,
        "travel_iters": 53,
        "ub": 16
      }
    ],
    "trains": 14
  },
  {
    "avg_tracks": 20.931034088134766,
    "conflicting_visit_pairs": 5915,
    "conflicts": 33,
    "delay_cost_type": "FiniteSteps123",
    "index": 48,
    "name": "stationA1",
    "solves": [
      {
        "algorithm_time": 0.021825256999999994,
        "avg_time_points": 5.086082059533387,
        "cost": 37,
        "delay_cost_type": "FiniteSteps123",
        "iterations": 188,
        "lb": 37,
        "max_time_points": 22,
        "num_conflicts": 4486,
        "num_time_points": 6322,
        "num_traveltime": 4486,
        "objective_iters": 37,
        "resource_iters": 1,
        "sol_time": 65.700801,
        "solver_name": "MaxSatDddLadderRC2",
        "solver_time": 0.043592442,
        "status": "ok",
        "total_time": 0.065417181,
        "travel_and_resource_iters": 110,
        "travel_iters": 39,
        "ub": 37
      }
    ],
    "trains": 29
  },
  {
    "avg_tracks": 19.0,
    "conflicting_visit_pairs": 3735,
    "conflicts": 33,
    "delay_cost_type": "FiniteSteps123",
    "index": 49,
    "name": "stationA2",
    "solves": [
      {
        "algorithm_time": 0.014079396,
        "avg_time_points": 5.214358974358975,
        "cost": 40,
        "delay_cost_type": "FiniteSteps123",
        "iterations": 160,
        "lb": 40,
        "max_time_points": 22,
        "num_conflicts": 3645,
        "num_time_points": 5084,
        "num_traveltime": 3645,
        "objective_iters": 40,
        "resource_iters": 1,
        "sol_time": 28.681504999999998,
        "solver_name": "MaxSatDddLadderRC2",
        "solver_time": 0.014349843,
        "status": "ok",
        "total_time": 0.028428742,
        "travel_and_resource_iters": 101,
        "travel_iters": 17,
        "ub": 40
      }
    ],
    "trains": 25
  },
  {
    "avg_tracks": 22.375,
    "conflicting_visit_pairs": 2061,
    "conflicts": 33,
    "delay_cost_type": "FiniteSteps123",
    "index": 50,
    "name": "stationA3",
    "solves": [
      {
        "algorithm_time": 0.012070003000000001,
        "avg_time_points": 3.7076502732240435,
        "cost": 19,
        "delay_cost_type": "FiniteSteps123",
        "iterations": 179,
        "lb": 19,
        "max_time_points": 13,
        "num_conflicts": 1824,
        "num_time_points": 2714,
        "num_traveltime": 1824,
        "objective_iters": 19,
        "resource_iters": 2,
        "sol_time": 17.806677999999998,
        "solver_name": "MaxSatDddLadderRC2",
        "solver_time": 0.005589261,
        "status": "ok",
        "total_time": 0.017658736,
        "travel_and_resource_iters": 52,
        "travel_iters": 105,
        "ub": 19
      }
    ],
    "trains": 16
  },
  {
    "avg_tracks": 19.214284896850586,
    "conflicting_visit_pairs": 1175,
    "conflicts": 33,
    "delay_cost_type": "FiniteSteps123",
    "index": 51,
    "name": "stationA4",
    "solves": [
      {
        "algorithm_time": 0.004211456000000001,
        "avg_time_points": 2.8369565217391304,
        "cost": 17,
        "delay_cost_type": "FiniteSteps123",
        "iterations": 103,
        "lb": 17,
        "max_time_points": 14,
        "num_conflicts": 917,
        "num_time_points": 1566,
        "num_traveltime": 917,
        "objective_iters": 17,
        "resource_iters": 1,
        "sol_time": 5.617234,
        "solver_name": "MaxSatDddLadderRC2",
        "solver_time": 0.001358012,
        "status": "ok",
        "total_time": 0.005568886,
        "travel_and_resource_iters": 40,
        "travel_iters": 44,
        "ub": 17
      }
    ],
    "trains": 14
  },
  {
    "avg_tracks": 19.25,
    "conflicting_visit_pairs": 876,
    "conflicts": 33,
    "delay_cost_type": "FiniteSteps123",
    "index": 52,
    "name": "stationA5",
    "solves": [
      {
        "algorithm_time": 0.003643246,
        "avg_time_points": 2.8649789029535864,
        "cost": 16,
        "delay_cost_type": "FiniteSteps123",
        "iterations": 103,
        "lb": 16,
        "max_time_points": 13,
        "num_conflicts": 809,
        "num_time_points": 1358,
        "num_traveltime": 809,
        "objective_iters": 16,
        "resource_iters": 1,
        "sol_time": 4.940327000000001,
        "solver_name": "MaxSatDddLadderRC2",
        "solver_time": 0.001254212,
        "status": "ok",
        "total_time": 0.004897016,
        "travel_and_resource_iters": 32,
        "travel_iters": 53,
        "ub": 16
      }
    ],
    "trains": 12
  },
  {
    "avg_tracks": 18.625,
    "conflicting_visit_pairs": 307,
    "conflicts": 33,
    "delay_cost_type": "FiniteSteps123",
    "index": 53,
    "name": "stationA6",
    "solves": [
      {
        "algorithm_time": 0.001137003,
        "avg_time_points": 1.6176470588235294,
        "cost": 10,
        "delay_cost_type": "FiniteSteps123",
        "iterations": 51,
        "lb": 10,
        "max_time_points": 5,
        "num_conflicts": 176,
        "num_time_points": 495,
        "num_traveltime": 176,
        "objective_iters": 10,
        "resource_iters": 1,
        "sol_time": 1.261423,
        "solver_name": "MaxSatDddLadderRC2",
        "solver_time": 0.000105796,
        "status": "ok",
        "total_time": 0.001242358,
        "travel_and_resource_iters": 4,
        "travel_iters": 35,
        "ub": 10
      }
    ],
    "trains": 8
  },
  {
    "avg_tracks": 12.625,
    "conflicting_visit_pairs": 126,
    "conflicts": 33,
    "delay_cost_type": "FiniteSteps123",
    "index": 54,
    "name": "stationA7",
    "solves": [
      {
        "algorithm_time": 0.002392145,
        "avg_time_points": 2.6285714285714286,
        "cost": 12,
        "delay_cost_type": "FiniteSteps123",
        "iterations": 104,
        "lb": 12,
        "max_time_points": 7,
        "num_conflicts": 323,
        "num_time_points": 552,
        "num_traveltime": 323,
        "objective_iters": 12,
        "resource_iters": 1,
        "sol_time": 2.948599,
        "solver_name": "MaxSatDddLadderRC2",
        "solver_time": 0.00051304,
        "status": "ok",
        "total_time": 0.002894107,
        "travel_and_resource_iters": 7,
        "travel_iters": 83,
        "ub": 12
      }
    ],
    "trains": 8
  },
  {
    "avg_tracks": 19.88888931274414,
    "conflicting_visit_pairs": 4862,
    "conflicts": 33,
    "delay_cost_type": "FiniteSteps123",
    "index": 55,
    "name": "stationA8",
    "solves": [
      {
        "algorithm_time": 0.04538907099999999,
        "avg_time_points": 9.970027247956404,
        "cost": 43,
        "delay_cost_type": "FiniteSteps123",
        "iterations": 265,
        "lb": 43,
        "max_time_points": 53,
        "num_conflicts": 8521,
        "num_time_points": 10977,
        "num_traveltime": 8521,
        "objective_iters": 43,
        "resource_iters": 3,
        "sol_time": 127.840119,
        "solver_name": "MaxSatDddLadderRC2",
        "solver_time": 0.082025316,
        "status": "ok",
        "total_time": 0.127413899,
        "travel_and_resource_iters": 172,
        "travel_iters": 46,
        "ub": 43
      }
    ],
    "trains": 27
  },
  {
    "avg_tracks": 20.049999237060547,
    "conflicting_visit_pairs": 2616,
    "conflicts": 33,
    "delay_cost_type": "FiniteSteps123",
    "index": 56,
    "name": "stationA9",
    "solves": [
      {
        "algorithm_time": 0.009075805,
        "avg_time_points": 3.44647201946472,
        "cost": 27,
        "delay_cost_type": "FiniteSteps123",
        "iterations": 164,
        "lb": 27,
        "max_time_points": 16,
        "num_conflicts": 1812,
        "num_time_points": 2833,
        "num_traveltime": 1812,
        "objective_iters": 27,
        "resource_iters": 1,
        "sol_time": 14.317003,
        "solver_name": "MaxSatDddLadderRC2",
        "solver_time": 0.005104438,
        "status": "ok",
        "total_time": 0.01417962,
        "travel_and_resource_iters": 59,
        "travel_iters": 76,
        "ub": 27
      }
    ],
    "trains": 20
  },
  {
    "avg_tracks": 18.176469802856445,
    "conflicting_visit_pairs": 1632,
    "conflicts": 33,
    "delay_cost_type": "FiniteSteps123",
    "index": 57,
    "name": "stationA10",
    "solves": [
      {
        "algorithm_time": 0.005046775,
        "avg_time_points": 2.705511811023622,
        "cost": 21,
        "delay_cost_type": "FiniteSteps123",
        "iterations": 113,
        "lb": 21,
        "max_time_points": 15,
        "num_conflicts": 948,
        "num_time_points": 1718,
        "num_traveltime": 948,
        "objective_iters": 21,
        "resource_iters": 1,
        "sol_time": 6.610691,
        "solver_name": "MaxSatDddLadderRC2",
        "solver_time": 0.001506424,
        "status": "ok",
        "total_time": 0.006552723,
        "travel_and_resource_iters": 49,
        "travel_iters": 41,
        "ub": 21
      }
    ],
    "trains": 17
  },
  {
    "avg_tracks": 20.482759475708008,
    "conflicting_visit_pairs": 6144,
    "conflicts": 33,
    "delay_cost_type": "FiniteSteps123",
    "index": 58,
    "name": "stationA11",
    "solves": [
      {
        "algorithm_time": 0.028909146999999982,
        "avg_time_points": 9.124897288414132,
        "cost": 41,
        "delay_cost_type": "FiniteSteps123",
        "iterations": 180,
        "lb": 41,
        "max_time_points": 83,
        "num_conflicts": 8344,
        "num_time_points": 11105,
        "num_traveltime": 8344,
        "objective_iters": 41,
        "resource_iters": 1,
        "sol_time": 153.26184600000002,
        "solver_name": "MaxSatDddLadderRC2",
        "solver_time": 0.123932675,
        "status": "ok",
        "total_time": 0.152841291,
        "travel_and_resource_iters": 125,
        "travel_iters": 12,
        "ub": 41
      }
    ],
    "trains": 29
  },
  {
    "avg_tracks": 21.714284896850586,
    "conflicting_visit_pairs": 6393,
    "conflicts": 33,
    "delay_cost_type": "FiniteSteps123",
    "index": 59,
    "name": "stationA12",
    "solves": [
      {
        "algorithm_time": 0.03301926100000001,
        "avg_time_points": 9.64790996784566,
        "cost": 44,
        "delay_cost_type": "FiniteSteps123",
        "iterations": 199,
        "lb": 44,
        "max_time_points": 85,
        "num_conflicts": 9007,
        "num_time_points": 12002,
        "num_traveltime": 9007,
        "objective_iters": 44,
        "resource_iters": 1,
        "sol_time": 131.072274,
        "solver_name": "MaxSatDddLadderRC2",
        "solver_time": 0.09755787,
        "status": "ok",
        "total_time": 0.130576549,
        "travel_and_resource_iters": 134,
        "travel_iters": 19,
        "ub": 44
      }
    ],
    "trains": 28
  },
  {
    "avg_tracks": 17.33333396911621,
    "conflicting_visit_pairs": 2022,
    "conflicts": 25,
    "delay_cost_type": "FiniteSteps123",
    "index": 60,
    "name": "stationB1",
    "solves": [
      {
        "algorithm_time": 0.006374679999999999,
        "avg_time_points": 2.970404984423676,
        "cost": 19,
        "delay_cost_type": "FiniteSteps123",
        "iterations": 114,
        "lb": 19,
        "max_time_points": 9,
        "num_conflicts": 1138,
        "num_time_points": 1907,
        "num_traveltime": 1138,
        "objective_iters": 19,
        "resource_iters": 1,
        "sol_time": 8.965231000000001,
        "solver_name": "MaxSatDddLadderRC2",
        "solver_time": 0.002502785,
        "status": "ok",
        "total_time": 0.008877091,
        "travel_and_resource_iters": 36,
        "travel_iters": 57,
        "ub": 19
      }
    ],
    "trains": 18
  },
  {
    "avg_tracks": 14.800000190734863,
    "conflicting_visit_pairs": 87,
    "conflicts": 25,
    "delay_cost_type": "FiniteSteps123",
    "index": 61,
    "name": "stationB2",
    "solves": [
      {
        "algorithm_time": 0.00155658,
        "avg_time_points": 1.7450980392156863,
        "cost": 7,
        "delay_cost_type": "FiniteSteps123",
        "iterations": 48,
        "lb": 7,
        "max_time_points": 4,
        "num_conflicts": 101,
        "num_time_points": 267,
        "num_traveltime": 101,
        "objective_iters": 7,
        "resource_iters": 1,
        "sol_time": 1.799625,
        "solver_name": "MaxSatDddLadderRC2",
        "solver_time": 0.000207858,
        "status": "ok",
        "total_time": 0.001763836,
        "travel_and_resource_iters": 3,
        "travel_iters": 36,
        "ub": 7
      }
    ],
    "trains": 5
  },
  {
    "avg_tracks": 16.799999237060547,
    "conflicting_visit_pairs": 136,
    "conflicts": 20,
    "delay_cost_type": "FiniteSteps123",
    "index": 62,
    "name": "stationB3",
    "solves": [
      {
        "algorithm_time": 0.0019627969999999996,
        "avg_time_points": 2.722543352601156,
        "cost": 5,
        "delay_cost_type": "FiniteSteps123",
        "iterations": 71,
        "lb": 5,
        "max_time_points": 7,
        "num_conflicts": 273,
        "num_time_points": 471,
        "num_traveltime": 273,
        "objective_iters": 5,
        "resource_iters": 1,
        "sol_time": 2.543929,
        "solver_name": "MaxSatDddLadderRC2",
        "solver_time": 0.000548661,
        "status": "ok",
        "total_time": 0.002510986,
        "travel_and_resource_iters": 10,
        "travel_iters": 54,
        "ub": 5
      }
    ],
    "trains": 5
  },
  {
    "avg_tracks": 15.949999809265137,
    "conflicting_visit_pairs": 2246,
    "conflicts": 25,
    "delay_cost_type": "FiniteSteps123",
    "index": 63,
    "name": "stationB4",
    "solves": [
      {
        "algorithm_time": 0.010385007000000002,
        "avg_time_points": 3.731003039513678,
        "cost": 31,
        "delay_cost_type": "FiniteSteps123",
        "iterations": 138,
        "lb": 31,
        "max_time_points": 13,
        "num_conflicts": 1608,
        "num_time_points": 2455,
        "num_traveltime": 1608,
        "objective_iters": 31,
        "resource_iters": 1,
        "sol_time": 13.878664,
        "solver_name": "MaxSatDddLadderRC2",
        "solver_time": 0.00334996,
        "status": "ok",
        "total_time": 0.013734464,
        "travel_and_resource_iters": 49,
        "travel_iters": 56,
        "ub": 31
      }
    ],
    "trains": 20
  },
  {
    "avg_tracks": 17.799999237060547,
    "conflicting_visit_pairs": 136,
    "conflicts": 25,
    "delay_cost_type": "FiniteSteps123",
    "index": 64,
    "name": "stationB5",
    "solves": [
      {
        "algorithm_time": 0.0017074000000000002,
        "avg_time_points": 3.8688524590163933,
        "cost": 6,
        "delay_cost_type": "FiniteSteps123",
        "iterations": 76,
        "lb": 6,
        "max_time_points": 13,
        "num_conflicts": 480,
        "num_time_points": 708,
        "num_traveltime": 480,
        "objective_iters": 6,
        "resource_iters": 1,
        "sol_time": 2.291945,
        "solver_name": "MaxSatDddLadderRC2",
        "solver_time": 0.000553687,
        "status": "ok",
        "total_time": 0.002260683,
        "travel_and_resource_iters": 27,
        "travel_iters": 41,
        "ub": 6
      }
    ],
    "trains": 5
  },
  {
    "avg_tracks": 15.199999809265137,
    "conflicting_visit_pairs": 93,
    "conflicts": 25,
    "delay_cost_type": "FiniteSteps123",
    "index": 65,
    "name": "stationB6",
    "solves": [
      {
        "algorithm_time": 0.00089369,
        "avg_time_points": 1.929936305732484,
        "cost": 5,
        "delay_cost_type": "FiniteSteps123",
        "iterations": 46,
        "lb": 5,
        "max_time_points": 4,
        "num_conflicts": 137,
        "num_time_points": 303,
        "num_traveltime": 137,
        "objective_iters": 5,
        "resource_iters": 1,
        "sol_time": 1.0140870000000002,
        "solver_name": "MaxSatDddLadderRC2",
        "solver_time": 0.000095533,
        "status": "ok",
        "total_time": 0.000988803,
        "travel_and_resource_iters": 3,
        "travel_iters": 36,
        "ub": 5
      }
    ],
    "trains": 5
  },
  {
    "avg_tracks": 15.25,
    "conflicting_visit_pairs": 2865,
    "conflicts": 25,
    "delay_cost_type": "FiniteSteps123",
    "index": 66,
    "name": "stationB7",
    "solves": [
      {
        "algorithm_time": 0.009064133,
        "avg_time_points": 4.4338624338624335,
        "cost": 40,
        "delay_cost_type": "FiniteSteps123",
        "iterations": 145,
        "lb": 40,
        "max_time_points": 18,
        "num_conflicts": 2324,
        "num_time_points": 3352,
        "num_traveltime": 2324,
        "objective_iters": 40,
        "resource_iters": 1,
        "sol_time": 20.17691,
        "solver_name": "MaxSatDddLadderRC2",
        "solver_time": 0.010959616,
        "status": "ok",
        "total_time": 0.020023184,
        "travel_and_resource_iters": 59,
        "travel_iters": 44,
        "ub": 40
      }
    ],
    "trains": 24
  },
  {
    "avg_tracks": 13.399999618530273,
    "conflicting_visit_pairs": 72,
    "conflicts": 25,
    "delay_cost_type": "FiniteSteps123",
    "index": 67,
    "name": "stationB8",
    "solves": [
      {
        "algorithm_time": 0.00158012,
        "avg_time_points": 2.460431654676259,
        "cost": 10,
        "delay_cost_type": "FiniteSteps123",
        "iterations": 83,
        "lb": 10,
        "max_time_points": 5,
        "num_conflicts": 190,
        "num_time_points": 342,
        "num_traveltime": 190,
        "objective_iters": 10,
        "resource_iters": 1,
        "sol_time": 1.835101,
        "solver_name": "MaxSatDddLadderRC2",
        "solver_time": 0.000228061,
        "status": "ok",
        "total_time": 0.001807795,
        "travel_and_resource_iters": 4,
        "travel_iters": 67,
        "ub": 10
      }
    ],
    "trains": 5
  },
  {
    "avg_tracks": 13.571428298950195,
    "conflicting_visit_pairs": 150,
    "conflicts": 25,
    "delay_cost_type": "FiniteSteps123",
    "index": 68,
    "name": "stationB9",
    "solves": [
      {
        "algorithm_time": 0.001663252,
        "avg_time_points": 3.015228426395939,
        "cost": 11,
        "delay_cost_type": "FiniteSteps123",
        "iterations": 67,
        "lb": 11,
        "max_time_points": 9,
        "num_conflicts": 338,
        "num_time_points": 594,
        "num_traveltime": 338,
        "objective_iters": 11,
        "resource_iters": 1,
        "sol_time": 2.0362489999999998,
        "solver_name": "MaxSatDddLadderRC2",
        "solver_time": 0.000345121,
        "status": "ok",
        "total_time": 0.002007823,
        "travel_and_resource_iters": 25,
        "travel_iters": 29,
        "ub": 11
      }
    ],
    "trains": 7
  },
  {
    "avg_tracks": 12.857142448425293,
    "conflicting_visit_pairs": 126,
    "conflicts": 25,
    "delay_cost_type": "FiniteSteps123",
    "index": 69,
    "name": "stationB10",
    "solves": [
      {
        "algorithm_time": 0.00099839,
        "avg_time_points": 1.6898395721925135,
        "cost": 11,
        "delay_cost_type": "FiniteSteps123",
        "iterations": 58,
        "lb": 11,
        "max_time_points": 5,
        "num_conflicts": 117,
        "num_time_points": 316,
        "num_traveltime": 117,
        "objective_iters": 11,
        "resource_iters": 1,
        "sol_time": 1.128101,
        "solver_name": "MaxSatDddLadderRC2",
        "solver_time": 0.000106484,
        "status": "ok",
        "total_time": 0.001104474,
        "travel_and_resource_iters": 4,
        "travel_iters": 41,
        "ub": 11
      }
    ],
    "trains": 7
  },
  {
    "avg_tracks": 15.399999618530273,
    "conflicting_visit_pairs": 3202,
    "conflicts": 25,
    "delay_cost_type": "FiniteSteps123",
    "index": 70,
    "name": "stationB11",
    "solves": [
      {
        "algorithm_time": 0.012465889,
        "avg_time_points": 4.20251572327044,
        "cost": 44,
        "delay_cost_type": "FiniteSteps123",
        "iterations": 145,
        "lb": 44,
        "max_time_points": 14,
        "num_conflicts": 2270,
        "num_time_points": 3341,
        "num_traveltime": 2270,
        "objective_iters": 44,
        "resource_iters": 1,
        "sol_time": 22.471728,
        "solver_name": "MaxSatDddLadderRC2",
        "solver_time": 0.009830932,
        "status": "ok",
        "total_time": 0.022296257,
        "travel_and_resource_iters": 56,
        "travel_iters": 43,
        "ub": 44
      }
    ],
    "trains": 25
  },
  {
    "avg_tracks": 16.214284896850586,
    "conflicting_visit_pairs": 970,
    "conflicts": 25,
    "delay_cost_type": "FiniteSteps123",
    "index": 71,
    "name": "stationB12",
    "solves": [
      {
        "algorithm_time": 0.005217082,
        "avg_time_points": 3.8034188034188032,
        "cost": 19,
        "delay_cost_type": "FiniteSteps123",
        "iterations": 127,
        "lb": 19,
        "max_time_points": 24,
        "num_conflicts": 1137,
        "num_time_points": 1780,
        "num_traveltime": 1137,
        "objective_iters": 19,
        "resource_iters": 1,
        "sol_time": 8.556543999999999,
        "solver_name": "MaxSatDddLadderRC2",
        "solver_time": 0.003267074,
        "status": "ok",
        "total_time": 0.008483524,
        "travel_and_resource_iters": 53,
        "travel_iters": 53,
        "ub": 19
      }
    ],
    "trains": 14
  }
]