[
  {
    "avg_tracks": 20.931034088134766,
    "conflicting_visit_pairs": 5915,
    "conflicts": 33,
    "delay_cost_type": "Continuous",
    "index": 0,
    "name": "origA1",
    "solves": [
      {
        "algorithm_time": 0.024763307,
        "avg_time_points": 2.150442477876106,
        "cost": 5526,
        "delay_cost_type": "Continuous",
        "iterations": 235,
        "lb": 5526,
        "max_time_points": 10,
        "num_conflicts": 1325,
        "num_time_points": 2673,
        "num_traveltime": 1325,
        "objective_iters": 36,
        "resource_iters": 1,
        "sol_time": 33.378265999999996,
        "solver_name": "MaxSatDddLadderRC2",
        "solver_time": 0.007796598,
        "status": "ok",
        "total_time": 0.032558978,
        "travel_and_resource_iters": 54,
        "travel_iters": 143,
        "ub": 5526
      }
    ],
    "trains": 29
  },
  {
    "avg_tracks": 19.0,
    "conflicting_visit_pairs": 3735,
    "conflicts": 33,
    "delay_cost_type": "Continuous",
    "index": 1,
    "name": "origA2",
    "solves": [
      {
        "algorithm_time": 0.017879153000000002,
        "avg_time_points": 2.2933333333333334,
        "cost": 5804,
        "delay_cost_type": "Continuous",
        "iterations": 221,
        "lb": 5804,
        "max_time_points": 20,
        "num_conflicts": 1130,
        "num_time_points": 2236,
        "num_traveltime": 1130,
        "objective_iters": 91,
        "resource_iters": 1,
        "sol_time": 51.157204,
        "solver_name": "MaxSatDddLadderRC2",
        "solver_time": 0.033052429,
        "status": "ok",
        "total_time": 0.050931029,
        "travel_and_resource_iters": 51,
        "travel_iters": 77,
        "ub": 5804
      }
    ],
    "trains": 25
  },
  {
    "avg_tracks": 22.375,
    "conflicting_visit_pairs": 2061,
    "conflicts": 33,
    "delay_cost_type": "Continuous",
    "index": 2,
    "name": "origA3",
    "solves": [
      {
        "algorithm_time": 0.00831292,
        "avg_time_points": 1.7677595628415301,
        "cost": 1329,
        "delay_cost_type": "Continuous",
        "iterations": 133,
        "lb": 1329,
        "max_time_points": 7,
        "num_conflicts": 524,
        "num_time_points": 1294,
        "num_traveltime": 524,
        "objective_iters": 27,
        "resource_iters": 1,
        "sol_time": 9.329657,
        "solver_name": "MaxSatDddLadderRC2",
        "solver_time": 0.000942958,
        "status": "ok",
        "total_time": 0.009255349,
        "travel_and_resource_iters": 15,
        "travel_iters": 91,
        "ub": 1329
      }
    ],
    "trains": 16
  },
  {
    "avg_tracks": 19.214284896850586,
    "conflicting_visit_pairs": 1175,
    "conflicts": 33,
    "delay_cost_type": "Continuous",
    "index": 3,
    "name": "origA4",
    "solves": [
      {
        "algorithm_time": 0.005584013,
        "avg_time_points": 1.9293478260869565,
        "cost": 2706,
        "delay_cost_type": "Continuous",
        "iterations": 98,
        "lb": 2706,
        "max_time_points": 8,
        "num_conflicts": 477,
        "num_time_points": 1065,
        "num_traveltime": 477,
        "objective_iters": 25,
        "resource_iters": 1,
        "sol_time": 6.2297769999999995,
        "solver_name": "MaxSatDddLadderRC2",
        "solver_time": 0.000571622,
        "status": "ok",
        "total_time": 0.006155014,
        "travel_and_resource_iters": 13,
        "travel_iters": 60,
        "ub": 2706
      }
    ],
    "trains": 14
  },
  {
    "avg_tracks": 19.25,
    "conflicting_visit_pairs": 876,
    "conflicts": 33,
    "delay_cost_type": "Continuous",
    "index": 4,
    "name": "origA5",
    "solves": [
      {
        "algorithm_time": 0.005072277,
        "avg_time_points": 1.9683544303797469,
        "cost": 2634,
        "delay_cost_type": "Continuous",
        "iterations": 104,
        "lb": 2634,
        "max_time_points": 8,
        "num_conflicts": 431,
        "num_time_points": 933,
        "num_traveltime": 431,
        "objective_iters": 15,
        "resource_iters": 1,
        "sol_time": 5.700425999999999,
        "solver_name": "MaxSatDddLadderRC2",
        "solver_time": 0.000578379,
        "status": "ok",
        "total_time": 0.00565009,
        "travel_and_resource_iters": 11,
        "travel_iters": 76,
        "ub": 2634
      }
    ],
    "trains": 12
  },
  {
    "avg_tracks": 18.625,
    "conflicting_visit_pairs": 307,
    "conflicts": 33,
    "delay_cost_type": "Continuous",
    "index": 5,
    "name": "origA6",
    "solves": [
      {
        "algorithm_time": 0.002858061,
        "avg_time_points": 1.738562091503268,
        "cost": 2043,
        "delay_cost_type": "Continuous",
        "iterations": 93,
        "lb": 2043,
        "max_time_points": 4,
        "num_conflicts": 218,
        "num_time_points": 532,
        "num_traveltime": 218,
        "objective_iters": 10,
        "resource_iters": 1,
        "sol_time": 3.23263,
        "solver_name": "MaxSatDddLadderRC2",
        "solver_time": 0.000340813,
        "status": "ok",
        "total_time": 0.003198316,
        "travel_and_resource_iters": 2,
        "travel_iters": 79,
        "ub": 2043
      }
    ],
    "trains": 8
  },
  {
    "avg_tracks": 12.625,
    "conflicting_visit_pairs": 126,
    "conflicts": 33,
    "delay_cost_type": "Continuous",
    "index": 6,
    "name": "origA7",
    "solves": [
      {
        "algorithm_time": 0.002324629,
        "avg_time_points": 2.657142857142857,
        "cost": 1918,
        "delay_cost_type": "Continuous",
        "iterations": 81,
        "lb": 1918,
        "max_time_points": 9,
        "num_conflicts": 330,
        "num_time_points": 558,
        "num_traveltime": 330,
        "objective_iters": 12,
        "resource_iters": 1,
        "sol_time": 2.670433,
        "solver_name": "MaxSatDddLadderRC2",
        "solver_time": 0.000323776,
        "status": "ok",
        "total_time": 0.002647951,
        "travel_and_resource_iters": 7,
        "travel_iters": 62,
        "ub": 1918
      }
    ],
    "trains": 8
  },
  {
    "avg_tracks": 19.214284896850586,
    "conflicting_visit_pairs": 4877,
    "conflicts": 33,
    "delay_cost_type": "Continuous",
    "index": 7,
    "name": "origA8",
    "solves": [
      {
        "algorithm_time": 0.1043576010000038,
        "avg_time_points": 5.625,
        "delay_cost_type": "Continuous",
        "iterations": 894,
        "lb": 22611,
        "max_time_points": 45,
        "num_conflicts": 4504,
        "num_time_points": 6210,
        "num_traveltime": 4504,
        "objective_iters": 748,
        "resource_iters": 1,
        "sol_time": 120593.60921699999,
        "solver_name": "MaxSatDddLadderRC2",
        "solver_time": 120.483950764,
        "status": "timeout",
        "total_time": 120.588307635,
        "travel_and_resource_iters": 140,
        "travel_iters": 5,
        "ub": 37305
      }
    ],
    "trains": 28
  },
  {
    "avg_tracks": 20.049999237060547,
    "conflicting_visit_pairs": 2616,
    "conflicts": 33,
    "delay_cost_type": "Continuous",
    "index": 8,
    "name": "origA9",
    "solves": [
      {
        "algorithm_time": 0.018439350000000004,
        "avg_time_points": 3.0985401459854014,
        "cost": 6178,
        "delay_cost_type": "Continuous",
        "iterations": 248,
        "lb": 6178,
        "max_time_points": 12,
        "num_conflicts": 1562,
        "num_time_points": 2547,
        "num_traveltime": 1562,
        "objective_iters": 66,
        "resource_iters": 1,
        "sol_time": 36.707162000000004,
        "solver_name": "MaxSatDddLadderRC2",
        "solver_time": 0.01811133,
        "status": "ok",
        "total_time": 0.036550118,
        "travel_and_resource_iters": 70,
        "travel_iters": 110,
        "ub": 6178
      }
    ],
    "trains": 20
  },
  {
    "avg_tracks": 18.176469802856445,
    "conflicting_visit_pairs": 1632,
    "conflicts": 33,
    "delay_cost_type": "Continuous",
    "index": 9,
    "name": "origA10",
    "solves": [
      {
        "algorithm_time": 0.011670498000000001,
        "avg_time_points": 3.2724409448818896,
        "cost": 4746,
        "delay_cost_type": "Continuous",
        "iterations": 213,
        "lb": 4746,
        "max_time_points": 13,
        "num_conflicts": 1323,
        "num_time_points": 2078,
        "num_traveltime": 1323,
        "objective_iters": 45,
        "resource_iters": 1,
        "sol_time": 23.327743,
        "solver_name": "MaxSatDddLadderRC2",
        "solver_time": 0.011523392,
        "status": "ok",
        "total_time": 0.023193345,
        "travel_and_resource_iters": 45,
        "travel_iters": 121,
        "ub": 4746
      }
    ],
    "trains": 17
  },
  {
    "avg_tracks": 19.83333396911621,
    "conflicting_visit_pairs": 6162,
    "conflicts": 33,
    "delay_cost_type": "Continuous",
    "index": 10,
    "name": "origA11",
    "solves": [
      {
        "algorithm_time": 0.0326603,
        "avg_time_points": 3.4008196721311474,
        "cost": 3331,
        "delay_cost_type": "Continuous",
        "iterations": 280,
        "lb": 3331,
        "max_time_points": 13,
        "num_conflicts": 2616,
        "num_time_points": 4149,
        "num_traveltime": 2616,
        "objective_iters": 142,
        "resource_iters": 1,
        "sol_time": 230.838706,
        "solver_name": "MaxSatDddLadderRC2",
        "solver_time": 0.197666155,
        "status": "ok",
        "total_time": 0.230325865,
        "travel_and_resource_iters": 97,
        "travel_iters": 39,
        "ub": 3331
      }
    ],
    "trains": 30
  },
  {
    "avg_tracks": 21.714284896850586,
    "conflicting_visit_pairs": 6393,
    "conflicts": 33,
    "delay_cost_type": "Continuous",
    "index": 11,
    "name": "origA12",
    "solves": [
      {
        "algorithm_time": 0.0688564859999996,
        "avg_time_points": 3.785369774919614,
        "cost": 4247,
        "delay_cost_type": "Continuous",
        "iterations": 535,
        "lb": 4247,
        "max_time_points": 15,
        "num_conflicts": 3121,
        "num_time_points": 4709,
        "num_traveltime": 3121,
        "objective_iters": 351,
        "resource_iters": 1,
        "sol_time": 12558.881576,
        "solver_name": "MaxSatDddLadderRC2",
        "solver_time": 12.487373688,
        "status": "ok",
        "total_time": 12.556229401,
        "travel_and_resource_iters": 98,
        "travel_iters": 84,
        "ub": 4247
      }
    ],
    "trains": 28
  },
  {
    "avg_tracks": 17.33333396911621,
    "conflicting_visit_pairs": 2022,
    "conflicts": 25,
    "delay_cost_type": "Continuous",
    "index": 12,
    "name": "origB1",
    "solves": [
      {
        "algorithm_time": 0.005086438,
        "avg_time_points": 1.250778816199377,
        "cost": 969,
        "delay_cost_type": "Continuous",
        "iterations": 92,
        "lb": 969,
        "max_time_points": 4,
        "num_conflicts": 152,
        "num_time_points": 803,
        "num_traveltime": 152,
        "objective_iters": 6,
        "resource_iters": 1,
        "sol_time": 5.334043,
        "solver_name": "MaxSatDddLadderRC2",
        "solver_time": 0.000204273,
        "status": "ok",
        "total_time": 0.005290234,
        "travel_and_resource_iters": 3,
        "travel_iters": 83,
        "ub": 969
      }
    ],
    "trains": 18
  },
  {
    "avg_tracks": 14.800000190734863,
    "conflicting_visit_pairs": 87,
    "conflicts": 25,
    "delay_cost_type": "Continuous",
    "index": 13,
    "name": "origB2",
    "solves": [
      {
        "algorithm_time": 0.001104356,
        "avg_time_points": 1.5163398692810457,
        "cost": 347,
        "delay_cost_type": "Continuous",
        "iterations": 52,
        "lb": 347,
        "max_time_points": 4,
        "num_conflicts": 71,
        "num_time_points": 232,
        "num_traveltime": 71,
        "objective_iters": 4,
        "resource_iters": 1,
        "sol_time": 1.30359,
        "solver_name": "MaxSatDddLadderRC2",
        "solver_time": 0.000181603,
        "status": "ok",
        "total_time": 0.001285303,
        "travel_and_resource_iters": 3,
        "travel_iters": 45,
        "ub": 347
      }
    ],
    "trains": 5
  },
  {
    "avg_tracks": 16.799999237060547,
    "conflicting_visit_pairs": 136,
    "conflicts": 20,
    "delay_cost_type": "Continuous",
    "index": 14,
    "name": "origB3",
    "solves": [
      {
        "algorithm_time": 0.001896029,
        "avg_time_points": 2.491329479768786,
        "cost": 629,
        "delay_cost_type": "Continuous",
        "iterations": 85,
        "lb": 629,
        "max_time_points": 6,
        "num_conflicts": 243,
        "num_time_points": 431,
        "num_traveltime": 243,
        "objective_iters": 10,
        "resource_iters": 1,
        "sol_time": 2.2204159999999997,
        "solver_name": "MaxSatDddLadderRC2",
        "solver_time": 0.000306699,
        "status": "ok",
        "total_time": 0.002202217,
        "travel_and_resource_iters": 6,
        "travel_iters": 69,
        "ub": 629
      }
    ],
    "trains": 5
  },
  {
    "avg_tracks": 15.949999809265137,
    "conflicting_visit_pairs": 2246,
    "conflicts": 25,
    "delay_cost_type": "Continuous",
    "index": 15,
    "name": "origB4",
    "solves": [
      {
        "algorithm_time": 0.007330691,
        "avg_time_points": 2.36322188449848,
        "cost": 53607,
        "delay_cost_type": "Continuous",
        "iterations": 120,
        "lb": 53607,
        "max_time_points": 19,
        "num_conflicts": 809,
        "num_time_points": 1555,
        "num_traveltime": 809,
        "objective_iters": 21,
        "resource_iters": 1,
        "sol_time": 10.222545,
        "solver_name": "MaxSatDddLadderRC2",
        "solver_time": 0.002829561,
        "status": "ok",
        "total_time": 0.010159729,
        "travel_and_resource_iters": 43,
        "travel_iters": 54,
        "ub": 53607
      }
    ],
    "trains": 20
  },
  {
    "avg_tracks": 17.799999237060547,
    "conflicting_visit_pairs": 136,
    "conflicts": 25,
    "delay_cost_type": "Continuous",
    "index": 16,
    "name": "origB5",
    "solves": [
      {
        "algorithm_time": 0.002210029,
        "avg_time_points": 1.7978142076502732,
        "cost": 288,
        "delay_cost_type": "Continuous",
        "iterations": 104,
        "lb": 288,
        "max_time_points": 4,
        "num_conflicts": 138,
        "num_time_points": 329,
        "num_traveltime": 138,
        "objective_iters": 4,
        "resource_iters": 1,
        "sol_time": 2.45383,
        "solver_name": "MaxSatDddLadderRC2",
        "solver_time": 0.000226264,
        "status": "ok",
        "total_time": 0.002435726,
        "travel_and_resource_iters": 3,
        "travel_iters": 97,
        "ub": 288
      }
    ],
    "trains": 5
  },
  {
    "avg_tracks": 15.199999809265137,
    "conflicting_visit_pairs": 93,
    "conflicts": 25,
    "delay_cost_type": "Continuous",
    "index": 17,
    "name": "origB6",
    "solves": [
      {
        "algorithm_time": 0.000916653,
        "avg_time_points": 1.3184713375796178,
        "cost": 176,
        "delay_cost_type": "Continuous",
        "iterations": 41,
        "lb": 176,
        "max_time_points": 3,
        "num_conflicts": 46,
        "num_time_points": 207,
        "num_traveltime": 46,
        "objective_iters": 3,
        "resource_iters": 1,
        "sol_time": 0.9815539999999999,
        "solver_name": "MaxSatDddLadderRC2",
        "solver_time": 0.000050619,
        "status": "ok",
        "total_time": 0.00096673,
        "travel_and_resource_iters": 1,
        "travel_iters": 37,
        "ub": 176
      }
    ],
    "trains": 5
  },
  {
    "avg_tracks": 15.25,
    "conflicting_visit_pairs": 2865,
    "conflicts": 25,
    "delay_cost_type": "Continuous",
    "index": 18,
    "name": "origB7",
    "solves": [
      {
        "algorithm_time": 0.036826512999999395,
        "avg_time_points": 3.562169312169312,
        "cost": 65828,
        "delay_cost_type": "Continuous",
        "iterations": 499,
        "lb": 65828,
        "max_time_points": 33,
        "num_conflicts": 1860,
        "num_time_points": 2693,
        "num_traveltime": 1860,
        "objective_iters": 364,
        "resource_iters": 1,
        "sol_time": 4737.413756000001,
        "solver_name": "MaxSatDddLadderRC2",
        "solver_time": 4.699459036,
        "status": "ok",
        "total_time": 4.736284962,
        "travel_and_resource_iters": 88,
        "travel_iters": 45,
        "ub": 65828
      }
    ],
    "trains": 24
  },
  {
    "avg_tracks": 13.399999618530273,
    "conflicting_visit_pairs": 72,
    "conflicts": 25,
    "delay_cost_type": "Continuous",
    "index": 19,
    "name": "origB8",
    "solves": [
      {
        "algorithm_time": 0.0007573230000000001,
        "avg_time_points": 1.2877697841726619,
        "cost": 676,
        "delay_cost_type": "Continuous",
        "iterations": 43,
        "lb": 676,
        "max_time_points": 2,
        "num_conflicts": 38,
        "num_time_points": 179,
        "num_traveltime": 38,
        "objective_iters": 5,
        "resource_iters": 1,
        "sol_time": 0.805483,
        "solver_name": "MaxSatDddLadderRC2",
        "solver_time": 0.000035473,
        "status": "ok",
        "total_time": 0.000792218,
        "travel_and_resource_iters": 0,
        "travel_iters": 38,
        "ub": 676
      }
    ],
    "trains": 5
  },
  {
    "avg_tracks": 13.571428298950195,
    "conflicting_visit_pairs": 150,
    "conflicts": 25,
    "delay_cost_type": "Continuous",
    "index": 20,
    "name": "origB9",
    "solves": [
      {
        "algorithm_time": 0.0028769579999999998,
        "avg_time_points": 3.081218274111675,
        "cost": 5967,
        "delay_cost_type": "Continuous",
        "iterations": 112,
        "lb": 5967,
        "max_time_points": 11,
        "num_conflicts": 383,
        "num_time_points": 607,
        "num_traveltime": 383,
        "objective_iters": 19,
        "resource_iters": 1,
        "sol_time": 3.634885,
        "solver_name": "MaxSatDddLadderRC2",
        "solver_time": 0.000725017,
        "status": "ok",
        "total_time": 0.003601546,
        "travel_and_resource_iters": 12,
        "travel_iters": 79,
        "ub": 5967
      }
    ],
    "trains": 7
  },
  {
    "avg_tracks": 11.375,
    "conflicting_visit_pairs": 130,
    "conflicts": 25,
    "delay_cost_type": "Continuous",
    "index": 21,
    "name": "origB10",
    "solves": [
      {
        "algorithm_time": 0.0020911239999999998,
        "avg_time_points": 2.763157894736842,
        "cost": 5747,
        "delay_cost_type": "Continuous",
        "iterations": 84,
        "lb": 5747,
        "max_time_points": 8,
        "num_conflicts": 307,
        "num_time_points": 525,
        "num_traveltime": 307,
        "objective_iters": 17,
        "resource_iters": 1,
        "sol_time": 2.483103,
        "solver_name": "MaxSatDddLadderRC2",
        "solver_time": 0.000363252,
        "status": "ok",
        "total_time": 0.00245399,
        "travel_and_resource_iters": 11,
        "travel_iters": 54,
        "ub": 5747
      }
    ],
    "trains": 8
  },
  {
    "avg_tracks": 15.399999618530273,
    "conflicting_visit_pairs": 3202,
    "conflicts": 25,
    "delay_cost_type": "Continuous",
    "index": 22,
    "name": "origB11",
    "solves": [
      {
        "algorithm_time": 0.09575978900001303,
        "avg_time_points": 4.355974842767296,
        "delay_cost_type": "Continuous",
        "iterations": 989,
        "lb": 75445,
        "max_time_points": 41,
        "num_conflicts": 2418,
        "num_time_points": 3463,
        "num_traveltime": 2418,
        "objective_iters": 832,
        "resource_iters": 1,
        "sol_time": 120114.764826,
        "solver_name": "MaxSatDddLadderRC2",
        "solver_time": 120.013677424,
        "status": "timeout",
        "total_time": 120.109436506,
        "travel_and_resource_iters": 140,
        "travel_iters": 16,
        "ub": 82885
      }
    ],
    "trains": 25
  },
  {
    "avg_tracks": 16.214284896850586,
    "conflicting_visit_pairs": 970,
    "conflicts": 25,
    "delay_cost_type": "Continuous",
    "index": 23,
    "name": "origB12",
    "solves": [
      {
        "algorithm_time": 0.0033716759999999997,
        "avg_time_points": 1.7072649572649572,
        "cost": 918,
        "delay_cost_type": "Continuous",
        "iterations": 54,
        "lb": 918,
        "max_time_points": 9,
        "num_conflicts": 287,
        "num_time_points": 799,
        "num_traveltime": 287,
        "objective_iters": 6,
        "resource_iters": 1,
        "sol_time": 3.5817129999999997,
        "solver_name": "MaxSatDddLadderRC2",
        "solver_time": 0.00017713,
        "status": "ok",
        "total_time": 0.003548238,
        "travel_and_resource_iters": 19,
        "travel_iters": 29,
        "ub": 918
      }
    ],
    "trains": 14
  },
  {
    "avg_tracks": 20.931034088134766,
    "conflicting_visit_pairs": 5915,
    "conflicts": 33,
    "delay_cost_type": "Continuous",
    "index": 24,
    "name": "trackA1",
    "solves": [
      {
        "algorithm_time": 0.04526825600000001,
        "avg_time_points": 4.522928399034594,
        "cost": 9621,
        "delay_cost_type": "Continuous",
        "iterations": 264,
        "lb": 9621,
        "max_time_points": 19,
        "num_conflicts": 3948,
        "num_time_points": 5622,
        "num_traveltime": 3948,
        "objective_iters": 94,
        "resource_iters": 2,
        "sol_time": 197.510366,
        "solver_name": "MaxSatDddLadderRC2",
        "solver_time": 0.151907611,
        "status": "ok",
        "total_time": 0.197175329,
        "travel_and_resource_iters": 100,
        "travel_iters": 67,
        "ub": 9621
      }
    ],
    "trains": 29
  },
  {
    "avg_tracks": 19.0,
    "conflicting_visit_pairs": 3735,
    "conflicts": 33,
    "delay_cost_type": "Continuous",
    "index": 25,
    "name": "trackA2",
    "solves": [
      {
        "algorithm_time": 0.05517220800000011,
        "avg_time_points": 4.278974358974359,
        "cost": 6859,
        "delay_cost_type": "Continuous",
        "iterations": 540,
        "lb": 6859,
        "max_time_points": 16,
        "num_conflicts": 2857,
        "num_time_points": 4172,
        "num_traveltime": 2857,
        "objective_iters": 347,
        "resource_iters": 1,
        "sol_time": 5058.98448,
        "solver_name": "MaxSatDddLadderRC2",
        "solver_time": 5.002147482,
        "status": "ok",
        "total_time": 5.057319112,
        "travel_and_resource_iters": 84,
        "travel_iters": 107,
        "ub": 6859
      }
    ],
    "trains": 25
  },
  {
    "avg_tracks": 22.375,
    "conflicting_visit_pairs": 2061,
    "conflicts": 33,
    "delay_cost_type": "Continuous",
    "index": 26,
    "name": "trackA3",
    "solves": [
      {
        "algorithm_time": 0.021635345,
        "avg_time_points": 3.7172131147540983,
        "cost": 2077,
        "delay_cost_type": "Continuous",
        "iterations": 281,
        "lb": 2077,
        "max_time_points": 13,
        "num_conflicts": 1816,
        "num_time_points": 2721,
        "num_traveltime": 1816,
        "objective_iters": 106,
        "resource_iters": 2,
        "sol_time": 180.66881600000002,
        "solver_name": "MaxSatDddLadderRC2",
        "solver_time": 0.158668286,
        "status": "ok",
        "total_time": 0.180303085,
        "travel_and_resource_iters": 58,
        "travel_iters": 114,
        "ub": 2077
      }
    ],
    "trains": 16
  },
  {
    "avg_tracks": 19.214284896850586,
    "conflicting_visit_pairs": 1175,
    "conflicts": 33,
    "delay_cost_type": "Continuous",
    "index": 27,
    "name": "trackA4",
    "solves": [
      {
        "algorithm_time": 0.007814094,
        "avg_time_points": 2.3442028985507246,
        "cost": 2069,
        "delay_cost_type": "Continuous",
        "iterations": 112,
        "lb": 2069,
        "max_time_points": 10,
        "num_conflicts": 677,
        "num_time_points": 1294,
        "num_traveltime": 677,
        "objective_iters": 14,
        "resource_iters": 1,
        "sol_time": 9.130306,
        "solver_name": "MaxSatDddLadderRC2",
        "solver_time": 0.00125225,
        "status": "ok",
        "total_time": 0.00906583,
        "travel_and_resource_iters": 20,
        "travel_iters": 76,
        "ub": 2069
      }
    ],
    "trains": 14
  },
  {
    "avg_tracks": 19.25,
    "conflicting_visit_pairs": 876,
    "conflicts": 33,
    "delay_cost_type": "Continuous",
    "index": 28,
    "name": "trackA5",
    "solves": [
      {
        "algorithm_time": 0.011752332000000004,
        "avg_time_points": 2.6666666666666665,
        "cost": 2773,
        "delay_cost_type": "Continuous",
        "iterations": 255,
        "lb": 2773,
        "max_time_points": 13,
        "num_conflicts": 713,
        "num_time_points": 1264,
        "num_traveltime": 713,
        "objective_iters": 138,
        "resource_iters": 2,
        "sol_time": 149.83183499999998,
        "solver_name": "MaxSatDddLadderRC2",
        "solver_time": 0.137707003,
        "status": "ok",
        "total_time": 0.149458785,
        "travel_and_resource_iters": 32,
        "travel_iters": 82,
        "ub": 2773
      }
    ],
    "trains": 12
  },
  {
    "avg_tracks": 18.625,
    "conflicting_visit_pairs": 307,
    "conflicts": 33,
    "delay_cost_type": "Continuous",
    "index": 29,
    "name": "trackA6",
    "solves": [
      {
        "algorithm_time": 0.003202182,
        "avg_time_points": 2.392156862745098,
        "cost": 1679,
        "delay_cost_type": "Continuous",
        "iterations": 98,
        "lb": 1679,
        "max_time_points": 9,
        "num_conflicts": 382,
        "num_time_points": 732,
        "num_traveltime": 382,
        "objective_iters": 13,
        "resource_iters": 1,
        "sol_time": 3.694194,
        "solver_name": "MaxSatDddLadderRC2",
        "solver_time": 0.00046961,
        "status": "ok",
        "total_time": 0.003671367,
        "travel_and_resource_iters": 20,
        "travel_iters": 65,
        "ub": 1679
      }
    ],
    "trains": 8
  },
  {
    "avg_tracks": 12.625,
    "conflicting_visit_pairs": 126,
    "conflicts": 33,
    "delay_cost_type": "Continuous",
    "index": 30,
    "name": "trackA7",
    "solves": [
      {
        "algorithm_time": 0.002601743,
        "avg_time_points": 2.4761904761904763,
        "cost": 1393,
        "delay_cost_type": "Continuous",
        "iterations": 94,
        "lb": 1393,
        "max_time_points": 6,
        "num_conflicts": 293,
        "num_time_points": 520,
        "num_traveltime": 293,
        "objective_iters": 9,
        "resource_iters": 1,
        "sol_time": 3.144657,
        "solver_name": "MaxSatDddLadderRC2",
        "solver_time": 0.000465789,
        "status": "ok",
        "total_time": 0.003067065,
        "travel_and_resource_iters": 8,
        "travel_iters": 75,
        "ub": 1393
      }
    ],
    "trains": 8
  },
  {
    "avg_tracks": 19.88888931274414,
    "conflicting_visit_pairs": 4862,
    "conflicts": 33,
    "delay_cost_type": "Continuous",
    "index": 31,
    "name": "trackA8",
    "solves": [
      {
        "algorithm_time": 0.12648668899998938,
        "avg_time_points": 5.673932788374206,
        "delay_cost_type": "Continuous",
        "iterations": 1159,
        "lb": 19888,
        "max_time_points": 32,
        "num_conflicts": 4365,
        "num_time_points": 6247,
        "num_traveltime": 4365,
        "objective_iters": 1110,
        "resource_iters": 1,
        "sol_time": 120842.37119600001,
        "solver_name": "MaxSatDddLadderRC2",
        "solver_time": 120.707898252,
        "status": "timeout",
        "total_time": 120.834383934,
        "travel_and_resource_iters": 48,
        "travel_iters": 0,
        "ub": 65133
      }
    ],
    "trains": 27
  },
  {
    "avg_tracks": 20.049999237060547,
    "conflicting_visit_pairs": 2616,
    "conflicts": 33,
    "delay_cost_type": "Continuous",
    "index": 32,
    "name": "trackA9",
    "solves": [
      {
        "algorithm_time": 0.030809821999999987,
        "avg_time_points": 4.828467153284672,
        "cost": 6305,
        "delay_cost_type": "Continuous",
        "iterations": 334,
        "lb": 6305,
        "max_time_points": 19,
        "num_conflicts": 2812,
        "num_time_points": 3969,
        "num_traveltime": 2812,
        "objective_iters": 166,
        "resource_iters": 1,
        "sol_time": 360.066322,
        "solver_name": "MaxSatDddLadderRC2",
        "solver_time": 0.328680706,
        "status": "ok",
        "total_time": 0.359489954,
        "travel_and_resource_iters": 108,
        "travel_iters": 58,
        "ub": 6305
      }
    ],
    "trains": 20
  },
  {
    "avg_tracks": 18.176469802856445,
    "conflicting_visit_pairs": 1632,
    "conflicts": 33,
    "delay_cost_type": "Continuous",
    "index": 33,
    "name": "trackA10",
    "solves": [
      {
        "algorithm_time": 0.010672273999999999,
        "avg_time_points": 2.878740157480315,
        "cost": 4812,
        "delay_cost_type": "Continuous",
        "iterations": 162,
        "lb": 4812,
        "max_time_points": 14,
        "num_conflicts": 1062,
        "num_time_points": 1828,
        "num_traveltime": 1062,
        "objective_iters": 58,
        "resource_iters": 1,
        "sol_time": 23.518046000000002,
        "solver_name": "MaxSatDddLadderRC2",
        "solver_time": 0.012715863,
        "status": "ok",
        "total_time": 0.023387592,
        "travel_and_resource_iters": 46,
        "travel_iters": 56,
        "ub": 4812
      }
    ],
    "trains": 17
  },
  {
    "avg_tracks": 20.482759475708008,
    "conflicting_visit_pairs": 6144,
    "conflicts": 33,
    "delay_cost_type": "Continuous",
    "index": 34,
    "name": "trackA11",
    "solves": [
      {
        "algorithm_time": 0.1398713540000074,
        "avg_time_points": 6.516023007395234,
        "delay_cost_type": "Continuous",
        "iterations": 1290,
        "lb": 7305,
        "max_time_points": 67,
        "num_conflicts": 5478,
        "num_time_points": 7930,
        "num_traveltime": 5478,
        "objective_iters": 1232,
        "resource_iters": 1,
        "sol_time": 120657.043315,
        "solver_name": "MaxSatDddLadderRC2",
        "solver_time": 120.50976514,
        "status": "timeout",
        "total_time": 120.649635879,
        "travel_and_resource_iters": 57,
        "travel_iters": 0,
        "ub": 74425
      }
    ],
    "trains": 29
  },
  {
    "avg_tracks": 21.714284896850586,
    "conflicting_visit_pairs": 6393,
    "conflicts": 33,
    "delay_cost_type": "Continuous",
    "index": 35,
    "name": "trackA12",
    "solves": [
      {
        "algorithm_time": 0.13102004400001022,
        "avg_time_points": 6.554662379421222,
        "delay_cost_type": "Continuous",
        "iterations": 1136,
        "lb": 8499,
        "max_time_points": 62,
        "num_conflicts": 5732,
        "num_time_points": 8154,
        "num_traveltime": 5732,
        "objective_iters": 1081,
        "resource_iters": 1,
        "sol_time": 120286.41150100001,
        "solver_name": "MaxSatDddLadderRC2",
        "solver_time": 120.147610362,
        "status": "timeout",
        "total_time": 120.278629669,
        "travel_and_resource_iters": 54,
        "travel_iters": 0,
        "ub": 100732
      }
    ],
    "trains": 28
  },
  {
    "avg_tracks": 17.33333396911621,
    "conflicting_visit_pairs": 2022,
    "conflicts": 25,
    "delay_cost_type": "Continuous",
    "index": 36,
    "name": "trackB1",
    "solves": [
      {
        "algorithm_time": 0.009341698999999998,
        "avg_time_points": 3.0109034267912773,
        "cost": 1507,
        "delay_cost_type": "Continuous",
        "iterations": 127,
        "lb": 1507,
        "max_time_points": 16,
        "num_conflicts": 1173,
        "num_time_points": 1933,
        "num_traveltime": 1173,
        "objective_iters": 51,
        "resource_iters": 1,
        "sol_time": 19.913774,
        "solver_name": "MaxSatDddLadderRC2",
        "solver_time": 0.010221831,
        "status": "ok",
        "total_time": 0.01956302,
        "travel_and_resource_iters": 45,
        "travel_iters": 29,
        "ub": 1507
      }
    ],
    "trains": 18
  },
  {
    "avg_tracks": 14.800000190734863,
    "conflicting_visit_pairs": 87,
    "conflicts": 25,
    "delay_cost_type": "Continuous",
    "index": 37,
    "name": "trackB2",
    "solves": [
      {
        "algorithm_time": 0.0020749849999999997,
        "avg_time_points": 1.973856209150327,
        "cost": 4404,
        "delay_cost_type": "Continuous",
        "iterations": 60,
        "lb": 4404,
        "max_time_points": 7,
        "num_conflicts": 130,
        "num_time_points": 302,
        "num_traveltime": 130,
        "objective_iters": 7,
        "resource_iters": 2,
        "sol_time": 2.378174,
        "solver_name": "MaxSatDddLadderRC2",
        "solver_time": 0.000266094,
        "status": "ok",
        "total_time": 0.00234046,
        "travel_and_resource_iters": 5,
        "travel_iters": 45,
        "ub": 4404
      }
    ],
    "trains": 5
  },
  {
    "avg_tracks": 16.799999237060547,
    "conflicting_visit_pairs": 136,
    "conflicts": 20,
    "delay_cost_type": "Continuous",
    "index": 38,
    "name": "trackB3",
    "solves": [
      {
        "algorithm_time": 0.002480544,
        "avg_time_points": 2.884393063583815,
        "cost": 596,
        "delay_cost_type": "Continuous",
        "iterations": 73,
        "lb": 596,
        "max_time_points": 8,
        "num_conflicts": 277,
        "num_time_points": 499,
        "num_traveltime": 277,
        "objective_iters": 6,
        "resource_iters": 1,
        "sol_time": 3.131401,
        "solver_name": "MaxSatDddLadderRC2",
        "solver_time": 0.000552794,
        "status": "ok",
        "total_time": 0.003032799,
        "travel_and_resource_iters": 22,
        "travel_iters": 43,
        "ub": 596
      }
    ],
    "trains": 5
  },
  {
    "avg_tracks": 15.949999809265137,
    "conflicting_visit_pairs": 2246,
    "conflicts": 25,
    "delay_cost_type": "Continuous",
    "index": 39,
    "name": "trackB4",
    "solves": [
      {
        "algorithm_time": 0.08754865799999578,
        "avg_time_points": 6.191489361702128,
        "cost": 60558,
        "delay_cost_type": "Continuous",
        "iterations": 921,
        "lb": 60558,
        "max_time_points": 35,
        "num_conflicts": 3042,
        "num_time_points": 4074,
        "num_traveltime": 3042,
        "objective_iters": 707,
        "resource_iters": 1,
        "sol_time": 51667.464315,
        "solver_name": "MaxSatDddLadderRC2",
        "solver_time": 51.575082483,
        "status": "ok",
        "total_time": 51.662630524,
        "travel_and_resource_iters": 141,
        "travel_iters": 71,
        "ub": 60558
      }
    ],
    "trains": 20
  },
  {
    "avg_tracks": 17.799999237060547,
    "conflicting_visit_pairs": 136,
    "conflicts": 25,
    "delay_cost_type": "Continuous",
    "index": 40,
    "name": "trackB5",
    "solves": [
      {
        "algorithm_time": 0.005684160999999999,
        "avg_time_points": 4.300546448087432,
        "cost": 1662,
        "delay_cost_type": "Continuous",
        "iterations": 101,
        "lb": 1662,
        "max_time_points": 12,
        "num_conflicts": 538,
        "num_time_points": 787,
        "num_traveltime": 538,
        "objective_iters": 19,
        "resource_iters": 2,
        "sol_time": 8.615796999999999,
        "solver_name": "MaxSatDddLadderRC2",
        "solver_time": 0.00287295,
        "status": "ok",
        "total_time": 0.008556436,
        "travel_and_resource_iters": 34,
        "travel_iters": 45,
        "ub": 1662
      }
    ],
    "trains": 5
  },
  {
    "avg_tracks": 15.199999809265137,
    "conflicting_visit_pairs": 93,
    "conflicts": 25,
    "delay_cost_type": "Continuous",
    "index": 41,
    "name": "trackB6",
    "solves": [
      {
        "algorithm_time": 0.001173596,
        "avg_time_points": 1.7070063694267517,
        "cost": 209,
        "delay_cost_type": "Continuous",
        "iterations": 52,
        "lb": 209,
        "max_time_points": 4,
        "num_conflicts": 105,
        "num_time_points": 268,
        "num_traveltime": 105,
        "objective_iters": 3,
        "resource_iters": 1,
        "sol_time": 1.319127,
        "solver_name": "MaxSatDddLadderRC2",
        "solver_time": 0.000112624,
        "status": "ok",
        "total_time": 0.001285767,
        "travel_and_resource_iters": 1,
        "travel_iters": 46,
        "ub": 209
      }
    ],
    "trains": 5
  },
  {
    "avg_tracks": 15.25,
    "conflicting_visit_pairs": 2865,
    "conflicts": 25,
    "delay_cost_type": "Continuous",
    "index": 42,
    "name": "trackB7",
    "solves": [
      {
        "algorithm_time": 0.021324064000000004,
        "avg_time_points": 3.8505291005291005,
        "cost": 56119,
        "delay_cost_type": "Continuous",
        "iterations": 245,
        "lb": 56119,
        "max_time_points": 19,
        "num_conflicts": 1896,
        "num_time_points": 2911,
        "num_traveltime": 1896,
        "objective_iters": 97,
        "resource_iters": 1,
        "sol_time": 126.31157200000001,
        "solver_name": "MaxSatDddLadderRC2",
        "solver_time": 0.104718948,
        "status": "ok",
        "total_time": 0.126042523,
        "travel_and_resource_iters": 72,
        "travel_iters": 74,
        "ub": 56119
      }
    ],
    "trains": 24
  },
  {
    "avg_tracks": 13.399999618530273,
    "conflicting_visit_pairs": 72,
    "conflicts": 25,
    "delay_cost_type": "Continuous",
    "index": 43,
    "name": "trackB8",
    "solves": [
      {
        "algorithm_time": 0.0033115769999999996,
        "avg_time_points": 3.20863309352518,
        "cost": 1906,
        "delay_cost_type": "Continuous",
        "iterations": 144,
        "lb": 1906,
        "max_time_points": 11,
        "num_conflicts": 273,
        "num_time_points": 446,
        "num_traveltime": 273,
        "objective_iters": 39,
        "resource_iters": 1,
        "sol_time": 5.369178,
        "solver_name": "MaxSatDddLadderRC2",
        "solver_time": 0.001969208,
        "status": "ok",
        "total_time": 0.005280141,
        "travel_and_resource_iters": 16,
        "travel_iters": 87,
        "ub": 1906
      }
    ],
    "trains": 5
  },
  {
    "avg_tracks": 13.571428298950195,
    "conflicting_visit_pairs": 150,
    "conflicts": 25,
    "delay_cost_type": "Continuous",
    "index": 44,
    "name": "trackB9",
    "solves": [
      {
        "algorithm_time": 0.005867034,
        "avg_time_points": 4.822335025380711,
        "cost": 8593,
        "delay_cost_type": "Continuous",
        "iterations": 155,
        "lb": 8593,
        "max_time_points": 15,
        "num_conflicts": 673,
        "num_time_points": 950,
        "num_traveltime": 673,
        "objective_iters": 47,
        "resource_iters": 1,
        "sol_time": 10.84336,
        "solver_name": "MaxSatDddLadderRC2",
        "solver_time": 0.004919778,
        "status": "ok",
        "total_time": 0.010786202,
        "travel_and_resource_iters": 35,
        "travel_iters": 71,
        "ub": 8593
      }
    ],
    "trains": 7
  },
  {
    "avg_tracks": 12.857142448425293,
    "conflicting_visit_pairs": 126,
    "conflicts": 25,
    "delay_cost_type": "Continuous",
    "index": 45,
    "name": "trackB10",
    "solves": [
      {
        "algorithm_time": 0.001126486,
        "avg_time_points": 1.5614973262032086,
        "cost": 6912,
        "delay_cost_type": "Continuous",
        "iterations": 45,
        "lb": 6912,
        "max_time_points": 4,
        "num_conflicts": 97,
        "num_time_points": 292,
        "num_traveltime": 97,
        "objective_iters": 7,
        "resource_iters": 1,
        "sol_time": 1.214426,
        "solver_name": "MaxSatDddLadderRC2",
        "solver_time": 0.000072037,
        "status": "ok",
        "total_time": 0.001198084,
        "travel_and_resource_iters": 2,
        "travel_iters": 36,
        "ub": 6912
      }
    ],
    "trains": 7
  },
  {
    "avg_tracks": 15.399999618530273,
    "conflicting_visit_pairs": 3202,
    "conflicts": 25,
    "delay_cost_type": "Continuous",
    "index": 46,
    "name": "trackB11",
    "solves": [
      {
        "algorithm_time": 0.018700548999999997,
        "avg_time_points": 4.0062893081761,
        "cost": 68844,
        "delay_cost_type": "Continuous",
        "iterations": 212,
        "lb": 68844,
        "max_time_points": 21,
        "num_conflicts": 2185,
        "num_time_points": 3185,
        "num_traveltime": 2185,
        "objective_iters": 76,
        "resource_iters": 1,
        "sol_time": 78.29779400000001,
        "solver_name": "MaxSatDddLadderRC2",
        "solver_time": 0.05939036,
        "status": "ok",
        "total_time": 0.078090261,
        "travel_and_resource_iters": 77,
        "travel_iters": 57,
        "ub": 68844
      }
    ],
    "trains": 25
  },
  {
    "avg_tracks": 16.214284896850586,
    "conflicting_visit_pairs": 970,
    "conflicts": 25,
    "delay_cost_type": "Continuous",
    "index": 47,
    "name": "trackB12",
    "solves": [
      {
        "algorithm_time": 0.1201598899999965,
        "avg_time_points": 3.6175213675213675,
        "delay_cost_type": "Continuous",
        "iterations": 1112,
        "lb": 14943,
        "max_time_points": 20,
        "num_conflicts": 1032,
        "num_time_points": 1693,
        "num_traveltime": 1032,
        "objective_iters": 1015,
        "resource_iters": 3,
        "sol_time": 120458.42927600001,
        "solver_name": "MaxSatDddLadderRC2",
        "solver_time": 120.327255498,
        "status": "timeout",
        "total_time": 120.447414659,
        "travel_and_resource_iters": 64,
        "travel_iters": 29,
        "ub": 27665
      }
    ],
    "trains": 14
  },
  {
    "avg_tracks": 20.931034088134766,
    "conflicting_visit_pairs": 5915,
    "conflicts": 33,
    "delay_cost_type": "Continuous",
    "index": 48,
    "name": "stationA1",
    "solves": [
      {
        "algorithm_time": 0.08215621099999737,
        "avg_time_points": 4.87288817377313,
        "delay_cost_type": "Continuous",
        "iterations": 703,
        "lb": 12402,
        "max_time_points": 19,
        "num_conflicts": 4237,
        "num_time_points": 6057,
        "num_traveltime": 4237,
        "objective_iters": 621,
        "resource_iters": 1,
        "sol_time": 120087.46976,
        "solver_name": "MaxSatDddLadderRC2",
        "solver_time": 120.001115993,
        "status": "timeout",
        "total_time": 120.083271564,
        "travel_and_resource_iters": 79,
        "travel_iters": 2,
        "ub": 33189
      }
    ],
    "trains": 29
  },
  {
    "avg_tracks": 19.0,
    "conflicting_visit_pairs": 3735,
    "conflicts": 33,
    "delay_cost_type": "Continuous",
    "index": 49,
    "name": "stationA2",
    "solves": [
      {
        "algorithm_time": 0.08900723700000412,
        "avg_time_points": 4.758974358974359,
        "delay_cost_type": "Continuous",
        "iterations": 793,
        "lb": 8343,
        "max_time_points": 20,
        "num_conflicts": 3221,
        "num_time_points": 4640,
        "num_traveltime": 3221,
        "objective_iters": 711,
        "resource_iters": 1,
        "sol_time": 120834.137424,
        "solver_name": "MaxSatDddLadderRC2",
        "solver_time": 120.739850788,
        "status": "timeout",
        "total_time": 120.828857327,
        "travel_and_resource_iters": 79,
        "travel_iters": 2,
        "ub": 19651
      }
    ],
    "trains": 25
  },
  {
    "avg_tracks": 22.375,
    "conflicting_visit_pairs": 2061,
    "conflicts": 33,
    "delay_cost_type": "Continuous",
    "index": 50,
    "name": "stationA3",
    "solves": [
      {
        "algorithm_time": 0.09028242200000136,
        "avg_time_points": 5.275956284153006,
        "cost": 3681,
        "delay_cost_type": "Continuous",
        "iterations": 889,
        "lb": 3681,
        "max_time_points": 19,
        "num_conflicts": 2863,
        "num_time_points": 3862,
        "num_traveltime": 2863,
        "objective_iters": 672,
        "resource_iters": 1,
        "sol_time": 86294.870226,
        "solver_name": "MaxSatDddLadderRC2",
        "solver_time": 86.199882574,
        "status": "ok",
        "total_time": 86.290164493,
        "travel_and_resource_iters": 100,
        "travel_iters": 115,
        "ub": 3681
      }
    ],
    "trains": 16
  },
  {
    "avg_tracks": 19.214284896850586,
    "conflicting_visit_pairs": 1175,
    "conflicts": 33,
    "delay_cost_type": "Continuous",
    "index": 51,
    "name": "stationA4",
    "solves": [
      {
        "algorithm_time": 0.013111782000000002,
        "avg_time_points": 3.7844202898550723,
        "cost": 3122,
        "delay_cost_type": "Continuous",
        "iterations": 202,
        "lb": 3122,
        "max_time_points": 17,
        "num_conflicts": 1412,
        "num_time_points": 2089,
        "num_traveltime": 1412,
        "objective_iters": 56,
        "resource_iters": 1,
        "sol_time": 35.535878,
        "solver_name": "MaxSatDddLadderRC2",
        "solver_time": 0.022214036,
        "status": "ok",
        "total_time": 0.035325373,
        "travel_and_resource_iters": 55,
        "travel_iters": 89,
        "ub": 3122
      }
    ],
    "trains": 14
  },
  {
    "avg_tracks": 19.25,
    "conflicting_visit_pairs": 876,
    "conflicts": 33,
    "delay_cost_type": "Continuous",
    "index": 52,
    "name": "stationA5",
    "solves": [
      {
        "algorithm_time": 0.014688053000000034,
        "avg_time_points": 3.6455696202531644,
        "cost": 3306,
        "delay_cost_type": "Continuous",
        "iterations": 284,
        "lb": 3306,
        "max_time_points": 17,
        "num_conflicts": 1136,
        "num_time_points": 1728,
        "num_traveltime": 1136,
        "objective_iters": 196,
        "resource_iters": 1,
        "sol_time": 325.85449500000004,
        "solver_name": "MaxSatDddLadderRC2",
        "solver_time": 0.310590977,
        "status": "ok",
        "total_time": 0.325278356,
        "travel_and_resource_iters": 52,
        "travel_iters": 34,
        "ub": 3306
      }
    ],
    "trains": 12
  },
  {
    "avg_tracks": 18.625,
    "conflicting_visit_pairs": 307,
    "conflicts": 33,
    "delay_cost_type": "Continuous",
    "index": 53,
    "name": "stationA6",
    "solves": [
      {
        "algorithm_time": 0.002584459,
        "avg_time_points": 1.7745098039215685,
        "cost": 2149,
        "delay_cost_type": "Continuous",
        "iterations": 62,
        "lb": 2149,
        "max_time_points": 6,
        "num_conflicts": 221,
        "num_time_points": 543,
        "num_traveltime": 221,
        "objective_iters": 9,
        "resource_iters": 1,
        "sol_time": 2.878831,
        "solver_name": "MaxSatDddLadderRC2",
        "solver_time": 0.000261035,
        "status": "ok",
        "total_time": 0.002845052,
        "travel_and_resource_iters": 6,
        "travel_iters": 45,
        "ub": 2149
      }
    ],
    "trains": 8
  },
  {
    "avg_tracks": 12.625,
    "conflicting_visit_pairs": 126,
    "conflicts": 33,
    "delay_cost_type": "Continuous",
    "index": 54,
    "name": "stationA7",
    "solves": [
      {
        "algorithm_time": 0.002634903,
        "avg_time_points": 2.7904761904761903,
        "cost": 1762,
        "delay_cost_type": "Continuous",
        "iterations": 112,
        "lb": 1762,
        "max_time_points": 8,
        "num_conflicts": 358,
        "num_time_points": 586,
        "num_traveltime": 358,
        "objective_iters": 17,
        "resource_iters": 1,
        "sol_time": 3.1601879999999998,
        "solver_name": "MaxSatDddLadderRC2",
        "solver_time": 0.000501308,
        "status": "ok",
        "total_time": 0.003135827,
        "travel_and_resource_iters": 7,
        "travel_iters": 86,
        "ub": 1762
      }
    ],
    "trains": 8
  },
  {
    "avg_tracks": 19.88888931274414,
    "conflicting_visit_pairs": 4862,
    "conflicts": 33,
    "delay_cost_type": "Continuous",
    "index": 55,
    "name": "stationA8",
    "solves": [
      {
        "algorithm_time": 0.1355293109999991,
        "avg_time_points": 5.10535876475931,
        "delay_cost_type": "Continuous",
        "iterations": 1374,
        "lb": 20817,
        "max_time_points": 30,
        "num_conflicts": 3816,
        "num_time_points": 5621,
        "num_traveltime": 3816,
        "objective_iters": 1327,
        "resource_iters": 1,
        "sol_time": 120032.244191,
        "solver_name": "MaxSatDddLadderRC2",
        "solver_time": 119.890795882,
        "status": "timeout",
        "total_time": 120.026324618,
        "travel_and_resource_iters": 46,
        "travel_iters": 0,
        "ub": 97714
      }
    ],
    "trains": 27
  },
  {
    "avg_tracks": 20.049999237060547,
    "conflicting_visit_pairs": 2616,
    "conflicts": 33,
    "delay_cost_type": "Continuous",
    "index": 56,
    "name": "stationA9",
    "solves": [
      {
        "algorithm_time": 0.08623774599999479,
        "avg_time_points": 4.742092457420925,
        "delay_cost_type": "Continuous",
        "iterations": 805,
        "lb": 7557,
        "max_time_points": 18,
        "num_conflicts": 2752,
        "num_time_points": 3898,
        "num_traveltime": 2752,
        "objective_iters": 692,
        "resource_iters": 1,
        "sol_time": 120222.21256,
        "solver_name": "MaxSatDddLadderRC2",
        "solver_time": 120.129290228,
        "status": "timeout",
        "total_time": 120.215527415,
        "travel_and_resource_iters": 82,
        "travel_iters": 30,
        "ub": 18660
      }
    ],
    "trains": 20
  },
  {
    "avg_tracks": 18.176469802856445,
    "conflicting_visit_pairs": 1632,
    "conflicts": 33,
    "delay_cost_type": "Continuous",
    "index": 57,
    "name": "stationA10",
    "solves": [
      {
        "algorithm_time": 0.042666785999999846,
        "avg_time_points": 3.9937007874015746,
        "cost": 6565,
        "delay_cost_type": "Continuous",
        "iterations": 590,
        "lb": 6565,
        "max_time_points": 23,
        "num_conflicts": 1699,
        "num_time_points": 2536,
        "num_traveltime": 1699,
        "objective_iters": 437,
        "resource_iters": 2,
        "sol_time": 6086.300653,
        "solver_name": "MaxSatDddLadderRC2",
        "solver_time": 6.041864878,
        "status": "ok",
        "total_time": 6.084531064,
        "travel_and_resource_iters": 81,
        "travel_iters": 69,
        "ub": 6565
      }
    ],
    "trains": 17
  },
  {
    "avg_tracks": 20.482759475708008,
    "conflicting_visit_pairs": 6144,
    "conflicts": 33,
    "delay_cost_type": "Continuous",
    "index": 58,
    "name": "stationA11",
    "solves": [
      {
        "algorithm_time": 0.14306068100000857,
        "avg_time_points": 4.7313064913722265,
        "delay_cost_type": "Continuous",
        "iterations": 1377,
        "lb": 4918,
        "max_time_points": 45,
        "num_conflicts": 3750,
        "num_time_points": 5758,
        "num_traveltime": 3750,
        "objective_iters": 1339,
        "resource_iters": 1,
        "sol_time": 120197.31941400001,
        "solver_name": "MaxSatDddLadderRC2",
        "solver_time": 120.046937101,
        "status": "timeout",
        "total_time": 120.189996787,
        "travel_and_resource_iters": 37,
        "travel_iters": 0,
        "ub": 71693
      }
    ],
    "trains": 29
  },
  {
    "avg_tracks": 21.714284896850586,
    "conflicting_visit_pairs": 6393,
    "conflicts": 33,
    "delay_cost_type": "Continuous",
    "index": 59,
    "name": "stationA12",
    "solves": [
      {
        "algorithm_time": 0.13159715700000163,
        "avg_time_points": 4.961414790996785,
        "delay_cost_type": "Continuous",
        "iterations": 1244,
        "lb": 6269,
        "max_time_points": 46,
        "num_conflicts": 4051,
        "num_time_points": 6172,
        "num_traveltime": 4051,
        "objective_iters": 1205,
        "resource_iters": 1,
        "sol_time": 120057.848922,
        "solver_name": "MaxSatDddLadderRC2",
        "solver_time": 119.91987153,
        "status": "timeout",
        "total_time": 120.051468129,
        "travel_and_resource_iters": 38,
        "travel_iters": 0,
        "ub": 98260
      }
    ],
    "trains": 28
  },
  {
    "avg_tracks": 17.33333396911621,
    "conflicting_visit_pairs": 2022,
    "conflicts": 25,
    "delay_cost_type": "Continuous",
    "index": 60,
    "name": "stationB1",
    "solves": [
      {
        "algorithm_time": 0.08344922299998814,
        "avg_time_points": 4.309968847352025,
        "cost": 4246,
        "delay_cost_type": "Continuous",
        "iterations": 812,
        "lb": 4246,
        "max_time_points": 17,
        "num_conflicts": 1935,
        "num_time_points": 2767,
        "num_traveltime": 1935,
        "objective_iters": 644,
        "resource_iters": 1,
        "sol_time": 82597.74990299999,
        "solver_name": "MaxSatDddLadderRC2",
        "solver_time": 82.508357239,
        "status": "ok",
        "total_time": 82.591805269,
        "travel_and_resource_iters": 56,
        "travel_iters": 110,
        "ub": 4246
      }
    ],
    "trains": 18
  },
  {
    "avg_tracks": 14.800000190734863,
    "conflicting_visit_pairs": 87,
    "conflicts": 25,
    "delay_cost_type": "Continuous",
    "index": 61,
    "name": "stationB2",
    "solves": [
      {
        "algorithm_time": 0.0014795639999999998,
        "avg_time_points": 1.8954248366013071,
        "cost": 4798,
        "delay_cost_type": "Continuous",
        "iterations": 49,
        "lb": 4798,
        "max_time_points": 6,
        "num_conflicts": 120,
        "num_time_points": 290,
        "num_traveltime": 120,
        "objective_iters": 8,
        "resource_iters": 1,
        "sol_time": 1.663056,
        "solver_name": "MaxSatDddLadderRC2",
        "solver_time": 0.000155165,
        "status": "ok",
        "total_time": 0.001634149,
        "travel_and_resource_iters": 4,
        "travel_iters": 35,
        "ub": 4798
      }
    ],
    "trains": 5
  },
  {
    "avg_tracks": 16.799999237060547,
    "conflicting_visit_pairs": 136,
    "conflicts": 20,
    "delay_cost_type": "Continuous",
    "index": 62,
    "name": "stationB3",
    "solves": [
      {
        "algorithm_time": 0.0017383569999999998,
        "avg_time_points": 2.959537572254335,
        "cost": 674,
        "delay_cost_type": "Continuous",
        "iterations": 75,
        "lb": 674,
        "max_time_points": 7,
        "num_conflicts": 313,
        "num_time_points": 512,
        "num_traveltime": 313,
        "objective_iters": 11,
        "resource_iters": 1,
        "sol_time": 2.078094,
        "solver_name": "MaxSatDddLadderRC2",
        "solver_time": 0.000311444,
        "status": "ok",
        "total_time": 0.002049319,
        "travel_and_resource_iters": 11,
        "travel_iters": 51,
        "ub": 674
      }
    ],
    "trains": 5
  },
  {
    "avg_tracks": 15.949999809265137,
    "conflicting_visit_pairs": 2246,
    "conflicts": 25,
    "delay_cost_type": "Continuous",
    "index": 63,
    "name": "stationB4",
    "solves": [
      {
        "algorithm_time": 0.045773868000000384,
        "avg_time_points": 4.993920972644377,
        "cost": 62616,
        "delay_cost_type": "Continuous",
        "iterations": 557,
        "lb": 62616,
        "max_time_points": 20,
        "num_conflicts": 2378,
        "num_time_points": 3286,
        "num_traveltime": 2378,
        "objective_iters": 410,
        "resource_iters": 1,
        "sol_time": 6528.73292,
        "solver_name": "MaxSatDddLadderRC2",
        "solver_time": 6.480829889,
        "status": "ok",
        "total_time": 6.526603156,
        "travel_and_resource_iters": 89,
        "travel_iters": 56,
        "ub": 62616
      }
    ],
    "trains": 20
  },
  {
    "avg_tracks": 17.799999237060547,
    "conflicting_visit_pairs": 136,
    "conflicts": 25,
    "delay_cost_type": "Continuous",
    "index": 64,
    "name": "stationB5",
    "solves": [
      {
        "algorithm_time": 0.003141105,
        "avg_time_points": 4.808743169398907,
        "cost": 1485,
        "delay_cost_type": "Continuous",
        "iterations": 107,
        "lb": 1485,
        "max_time_points": 20,
        "num_conflicts": 651,
        "num_time_points": 880,
        "num_traveltime": 651,
        "objective_iters": 21,
        "resource_iters": 1,
        "sol_time": 4.749586,
        "solver_name": "MaxSatDddLadderRC2",
        "solver_time": 0.001541929,
        "status": "ok",
        "total_time": 0.00468233,
        "travel_and_resource_iters": 46,
        "travel_iters": 38,
        "ub": 1485
      }
    ],
    "trains": 5
  },
  {
    "avg_tracks": 15.199999809265137,
    "conflicting_visit_pairs": 93,
    "conflicts": 25,
    "delay_cost_type": "Continuous",
    "index": 65,
    "name": "stationB6",
    "solves": [
      {
        "algorithm_time": 0.001100247,
        "avg_time_points": 1.929936305732484,
        "cost": 461,
        "delay_cost_type": "Continuous",
        "iterations": 46,
        "lb": 461,
        "max_time_points": 4,
        "num_conflicts": 137,
        "num_time_points": 303,
        "num_traveltime": 137,
        "objective_iters": 5,
        "resource_iters": 1,
        "sol_time": 1.210895,
        "solver_name": "MaxSatDddLadderRC2",
        "solver_time": 0.000081302,
        "status": "ok",
        "total_time": 0.001180936,
        "travel_and_resource_iters": 3,
        "travel_iters": 36,
        "ub": 461
      }
    ],
    "trains": 5
  },
  {
    "avg_tracks": 15.25,
    "conflicting_visit_pairs": 2865,
    "conflicts": 25,
    "delay_cost_type": "Continuous",
    "index": 66,
    "name": "stationB7",
    "solves": [
      {
        "algorithm_time": 0.05122378999999988,
        "avg_time_points": 4.964285714285714,
        "cost": 59333,
        "delay_cost_type": "Continuous",
        "iterations": 563,
        "lb": 59333,
        "max_time_points": 18,
        "num_conflicts": 2672,
        "num_time_points": 3753,
        "num_traveltime": 2672,
        "objective_iters": 417,
        "resource_iters": 1,
        "sol_time": 10188.188436,
        "solver_name": "MaxSatDddLadderRC2",
        "solver_time": 10.134550954,
        "status": "ok",
        "total_time": 10.185774206,
        "travel_and_resource_iters": 90,
        "travel_iters": 54,
        "ub": 59333
      }
    ],
    "trains": 24
  },
  {
    "avg_tracks": 13.399999618530273,
    "conflicting_visit_pairs": 72,
    "conflicts": 25,
    "delay_cost_type": "Continuous",
    "index": 67,
    "name": "stationB8",
    "solves": [
      {
        "algorithm_time": 0.0034219949999999997,
        "avg_time_points": 2.5251798561151078,
        "cost": 2300,
        "delay_cost_type": "Continuous",
        "iterations": 95,
        "lb": 2300,
        "max_time_points": 6,
        "num_conflicts": 193,
        "num_time_points": 351,
        "num_traveltime": 193,
        "objective_iters": 11,
        "resource_iters": 1,
        "sol_time": 4.211462,
        "solver_name": "MaxSatDddLadderRC2",
        "solver_time": 0.000683563,
        "status": "ok",
        "total_time": 0.004104979,
        "travel_and_resource_iters": 7,
        "travel_iters": 75,
        "ub": 2300
      }
    ],
    "trains": 5
  },
  {
    "avg_tracks": 13.571428298950195,
    "conflicting_visit_pairs": 150,
    "conflicts": 25,
    "delay_cost_type": "Continuous",
    "index": 68,
    "name": "stationB9",
    "solves": [
      {
        "algorithm_time": 0.0035895019999999996,
        "avg_time_points": 3.6395939086294415,
        "cost": 12006,
        "delay_cost_type": "Continuous",
        "iterations": 102,
        "lb": 12006,
        "max_time_points": 9,
        "num_conflicts": 454,
        "num_time_points": 717,
        "num_traveltime": 454,
        "objective_iters": 17,
        "resource_iters": 1,
        "sol_time": 4.9955989999999995,
        "solver_name": "MaxSatDddLadderRC2",
        "solver_time": 0.001380153,
        "status": "ok",
        "total_time": 0.004969148,
        "travel_and_resource_iters": 32,
        "travel_iters": 51,
        "ub": 12006
      }
    ],
    "trains": 7
  },
  {
    "avg_tracks": 12.857142448425293,
    "conflicting_visit_pairs": 126,
    "conflicts": 25,
    "delay_cost_type": "Continuous",
    "index": 69,
    "name": "stationB10",
    "solves": [
      {
        "algorithm_time": 0.000964956,
        "avg_time_points": 1.5454545454545454,
        "cost": 8761,
        "delay_cost_type": "Continuous",
        "iterations": 48,
        "lb": 8761,
        "max_time_points": 4,
        "num_conflicts": 92,
        "num_time_points": 289,
        "num_traveltime": 92,
        "objective_iters": 7,
        "resource_iters": 1,
        "sol_time": 1.052851,
        "solver_name": "MaxSatDddLadderRC2",
        "solver_time": 0.000071241,
        "status": "ok",
        "total_time": 0.001035798,
        "travel_and_resource_iters": 3,
        "travel_iters": 36,
        "ub": 8761
      }
    ],
    "trains": 7
  },
  {
    "avg_tracks": 15.399999618530273,
    "conflicting_visit_pairs": 3202,
    "conflicts": 25,
    "delay_cost_type": "Continuous",
    "index": 70,
    "name": "stationB11",
    "solves": [
      {
        "algorithm_time": 0.051756837999999306,
        "avg_time_points": 4.662893081761006,
        "cost": 72973,
        "delay_cost_type": "Continuous",
        "iterations": 538,
        "lb": 72973,
        "max_time_points": 17,
        "num_conflicts": 2598,
        "num_time_points": 3707,
        "num_traveltime": 2598,
        "objective_iters": 441,
        "resource_iters": 1,
        "sol_time": 12989.013439,
        "solver_name": "MaxSatDddLadderRC2",
        "solver_time": 12.934655272,
        "status": "ok",
        "total_time": 12.986411354,
        "travel_and_resource_iters": 72,
        "travel_iters": 23,
        "ub": 72973
      }
    ],
    "trains": 25
  },
  {
    "avg_tracks": 16.214284896850586,
    "conflicting_visit_pairs": 970,
    "conflicts": 25,
    "delay_cost_type": "Continuous",
    "index": 71,
    "name": "stationB12",
    "solves": [
      {
        "algorithm_time": 0.1278609420000123,
        "avg_time_points": 3.5106837606837606,
        "delay_cost_type": "Continuous",
        "iterations": 1244,
        "lb": 16563,
        "max_time_points": 23,
        "num_conflicts": 993,
        "num_time_points": 1643,
        "num_traveltime": 993,
        "objective_iters": 1200,
        "resource_iters": 1,
        "sol_time": 120392.098615,
        "solver_name": "MaxSatDddLadderRC2",
        "solver_time": 120.254077285,
        "status": "timeout",
        "total_time": 120.381937738,
        "travel_and_resource_iters": 41,
        "travel_iters": 2,
        "ub": 27669
      }
    ],
    "trains": 14
  }
]